{"03A62786E64F394D":[{"a":"2022","h":"03A62786E64F394D","g":"LE2022_106","k":"Lindström, Jan (SWE)","p":"106","i":"H","o":"Herrar 60-","j":"Team Norrvik","l":"166","m":"188","b":"04:05:18","n":"13.45","q":"Finished","f":"04:05:18","e":"04:05:18","c":"13.45","d":"166"},{"a":"2023","h":"03A62786E64F394D","g":"LE2023_615","k":"Lindström, Jan (SWE)","p":"615","i":"H","o":"Herrar 60-","j":"Källbottens IK","l":"203","m":"234","b":"03:57:21","n":"13.90","q":"Finished","f":"03:57:21","e":"03:57:21","c":"13.90","d":"203"}],"FE8440DD7FE8864D":[{"a":"2023","h":"FE8440DD7FE8864D","g":"LE2023_46","k":"Larsson, David (SWE)","p":"46","i":"H","o":"Herrar 19-39","j":"Lillhärdals IF","l":"37","m":"37","b":"02:28:04","n":"22.29","q":"Finished","f":"02:28:04","e":"02:28:04","c":"22.29","d":"37"}],"8FDE79B9280ADA4D":[{"a":"2023","h":"8FDE79B9280ADA4D","g":"LE2023_676","k":"Thorell, Douglas (SWE)","p":"676","i":"H","o":"Herrar 19-39","j":"Tänndalens IF","l":"141","m":"159","b":"03:10:26","n":"17.33","q":"Finished","f":"03:10:26","e":"03:10:26","c":"17.33","d":"141"},{"a":"2024","h":"8FDE79B9280ADA4D","g":"LE2024_242","k":"Thorell, Douglas (SWE)","p":"242","i":"H","o":"Herrar 21-39","j":"Tänndalen IF","l":"96","m":"102","b":"02:43:38","n":"20.17","q":"Finished","f":"02:43:38","e":"02:43:38","c":"20.17","d":"96"}],"1F42F826D02F034D":[{"a":"2023","h":"1F42F826D02F034D","g":"LE2023_685","k":"Olsson, Joakim (SWE)","p":"685","i":"H","o":"Herrar 40-49","j":"Hällbybrunns IF","l":"46","m":"46","b":"02:31:13","n":"21.82","q":"Finished","f":"02:31:13","e":"02:31:13","c":"21.82","d":"46"},{"a":"2024","h":"1F42F826D02F034D","g":"LE2024_41","k":"Olsson, Joakim (SWE)","p":"41","i":"H","o":"Herrar 40-49","j":"Hällbybrunns IF","l":"70","m":"72","b":"02:36:21","n":"21.11","q":"Finished","f":"02:36:21","e":"02:36:21","c":"21.11","d":"70"},{"a":"2025","h":"1F42F826D02F034D","g":"LE2025_253","k":"Olsson, Joakim (SWE)","p":"253","i":"H","o":"Herrar 50-59","j":"Hällbybrunns IF","l":"60","m":"62","b":"02:48:13","n":"19.62","q":"Finished","f":"02:48:13","e":"02:48:13","c":"19.62","d":"60"},{"a":"2026","h":"1F42F826D02F034D","g":"LE2026_53","k":"Olsson, Joakim (SWE)","p":"53","i":"H","o":"Herrar 50-59","j":"Hällbybrunns IF","l":"51","m":"51","b":"02:50:44","n":"19.33","q":"Finished","f":"02:50:44","e":"02:50:44","c":"19.33","d":"51"}],"76BE2A59A54EEA4D":[{"a":"2023","h":"76BE2A59A54EEA4D","g":"LE2023_349","k":"Bäckström, Christer (SWE)","p":"349","i":"H","o":"Herrar 50-59","j":"IK Aluminium","l":"242","m":"284","b":"DNS","q":"Finished","f":"DNS","e":"DNS","d":"242"},{"a":"2024","h":"76BE2A59A54EEA4D","g":"LE2024_101","k":"Bäckström, Christer (SWE)","p":"101","i":"H","o":"Herrar 50-59","j":"IK Aluminium","l":"120","m":"132","b":"02:49:35","n":"19.46","q":"Finished","f":"02:49:35","e":"02:49:35","c":"19.46","d":"120"}],"004E8B0B3793474D":[{"a":"2025","h":"004E8B0B3793474D","g":"LE2025_108","k":"Marthinussen, Gøran (NOR)","p":"108","i":"H","o":"Herrar 40-49","j":"Gutta Krutt / Guttakrutt","l":"220","m":"265","b":"04:49:51","n":"11.39","q":"Finished","f":"04:49:51","e":"04:49:51","c":"11.39","d":"220"}],"979DE4953324164D":[{"a":"2025","h":"979DE4953324164D","g":"LE2025_291","k":"Ward, Niclas (SWE)","p":"291","i":"H","o":"Herrar 50-59","j":"Wickström Coaching","l":"174","m":"204","b":"03:41:18","n":"14.91","q":"Finished","f":"03:41:18","e":"03:41:18","c":"14.91","d":"174"}],"8970C79B5F86564D":[{"a":"2026","h":"8970C79B5F86564D","g":"LE2026_315","k":"Ingre, Robert (SWE)","p":"315","i":"H","o":"Herrar 21-39","j":"AXA SC","l":"216","m":"250","b":"04:11:41","n":"13.11","q":"Finished","f":"04:11:41","e":"04:11:41","c":"13.11","d":"216"}]}