{"999999167888590000117D0A":[{"a":"2014","B":"999999167888590000117D0A","A":"9999991678885900001BF491","R":"Holme, Cathrine (NOR)","ap":"2075","C":"D45","ao":"UL-90","D":"Romerike Ultraløperklubb","Y":"14","Z":"4","aa":"238","b":"09:45:43","ar":"I mål","aq":"05:00:00","Q":"7","ah":"05:55:28","am":"00:55:28","al":"55:28","aj":"06:17","ai":"9.56","ak":"37","K":"07:25:32","P":"02:25:32","O":"01:30:04","M":"06:14","L":"9.63","N":"27","ab":"08:32:51","ag":"03:32:51","af":"01:07:19","ad":"06:18","ac":"9.54","ae":"22","i":"09:51:45","n":"04:51:45","m":"01:18:54","k":"06:29","j":"9.28","l":"17","S":"11:35:29","X":"06:35:29","W":"01:43:44","U":"07:07","T":"8.45","V":"16","u":"12:39:41","z":"07:39:41","y":"01:04:12","w":"07:08","v":"8.41","x":"15","c":"13:46:32","h":"08:46:32","g":"01:06:51","e":"06:46","d":"8.89","f":"14","E":"14:45:43","J":"09:45:43","I":"59:11","G":"05:45","F":"10.44","H":"14"}],"9999991678886F0001C6EF0A":[{"a":"2014","B":"9999991678886F0001C6EF0A","A":"9999991678885900001DB872","R":"Karlsson, Niklas (SWE)","ap":"1757","C":"H21","ao":"UL-90","D":"IFK Mora FIK","Y":"24","Z":"11","aa":"28","b":"07:37:42","ar":"I mål","aq":"05:00:00","Q":"6","ah":"05:42:24","am":"00:42:24","al":"42:24","aj":"04:48","ai":"12.51","ak":"32","K":"06:52:39","P":"01:52:39","O":"01:10:15","M":"04:52","L":"12.35","N":"32","ab":"07:44:37","ag":"02:44:37","af":"51:58","ad":"04:52","ac":"12.35","ae":"32","i":"08:46:02","n":"03:46:02","m":"01:01:25","k":"05:03","j":"11.92","l":"28","S":"10:04:45","X":"05:04:45","W":"01:18:43","U":"05:24","T":"11.13","V":"25","u":"10:54:27","z":"05:54:27","y":"49:42","w":"05:32","v":"10.87","x":"24","c":"11:52:39","h":"06:52:39","g":"58:12","e":"05:53","d":"10.20","f":"24","E":"12:37:42","J":"07:37:42","I":"45:03","G":"04:23","F":"13.72","H":"24"}],"99999916788859000011780A":[{"a":"2014","B":"99999916788859000011780A","A":"9999991678885900001BEDE6","R":"Kämpelycke, Christina (SWE)","ap":"2033","C":"D35","ao":"UL-90","D":"LF Lejonbragden","ar":"Brutit","aq":"05:00:00","ah":"05:58:37","am":"00:58:37","al":"58:37","aj":"06:38","ai":"9.05","ak":"55","K":"07:37:44","P":"02:37:44","O":"01:39:07","M":"06:52","L":"8.75","N":"55","ab":"09:00:29","ag":"04:00:29","af":"01:22:45","ad":"07:45","ac":"7.76","ae":"63","i":"10:56:57","n":"05:56:57","m":"01:56:28","k":"09:33","j":"6.29","l":"80"},{"a":"2015","B":"99999916788859000011780A","A":"9999991678885A00001FA7E4","R":"Kämpelycke, Christina (SWE)","ap":"3137","C":"W35","ao":"UL-90","D":"LF Lejonbragden","Y":"122","Z":"23","aa":"735","b":"12:51:58","ar":"I mål","aq":"05:00:00","ah":"06:01:34","am":"01:01:34","al":"01:01:34","aj":"06:58","ai":"8.62","ak":"106","K":"07:45:40","P":"02:45:40","O":"01:44:06","M":"07:12","L":"8.34","N":"113","ab":"09:08:17","ag":"04:08:17","af":"01:22:37","ad":"07:44","ac":"7.77","ae":"111","i":"10:58:14","n":"05:58:14","m":"01:49:57","k":"09:01","j":"6.66","l":"122","S":"13:06:31","X":"08:06:31","W":"02:08:17","U":"08:48","T":"6.83","V":"114","u":"14:34:12","z":"09:34:12","y":"01:27:41","w":"09:45","v":"6.16","x":"113","c":"16:21:06","h":"11:21:06","g":"01:46:54","e":"10:48","d":"5.56","f":"118","E":"17:51:58","J":"12:51:58","I":"01:30:52","G":"08:50","F":"6.80","H":"122"},{"a":"2016","B":"99999916788859000011780A","A":"9999991678885A00002219D5","R":"Kämpelycke, Christina (SWE)","ap":"3034","C":"W35","ao":"UL-90","D":"Axa Sport Club","ar":"Startade inte","aq":"05:00:00"}],"9999991678885900000CA10A":[{"a":"2014","B":"9999991678885900000CA10A","A":"9999991678885900001BFA84","R":"Lindberg, Johan (SWE)","ap":"1518","C":"H21","ao":"UL-90","D":"Mora Brandkårs Ultrateam","Y":"526","Z":"111","aa":"595","b":"12:22:04","ar":"I mål","aq":"05:00:00","Q":"4","ah":"06:09:16","am":"01:09:16","al":"01:09:16","aj":"07:51","ai":"7.66","ak":"639","K":"07:54:49","P":"02:54:49","O":"01:45:33","M":"07:18","L":"8.22","N":"625","ab":"09:12:09","ag":"04:12:09","af":"01:17:20","ad":"07:14","ac":"8.30","ae":"575","i":"10:54:21","n":"05:54:21","m":"01:42:12","k":"08:23","j":"7.16","l":"582","S":"13:14:07","X":"08:14:07","W":"02:19:46","U":"09:35","T":"6.27","V":"559","u":"14:40:41","z":"09:40:41","y":"01:26:34","w":"09:38","v":"6.24","x":"553","c":"16:13:37","h":"11:13:37","g":"01:32:56","e":"09:24","d":"6.39","f":"545","E":"17:22:04","J":"12:22:04","I":"01:08:27","G":"06:39","F":"9.03","H":"526"}],"9999991678885900000E250A":[{"a":"2014","B":"9999991678885900000E250A","A":"9999991678885900001BEE95","R":"Palmgren, Göran (SWE)","ap":"1134","C":"H45","ao":"UL-90","D":"Sätra IF","Y":"142","Z":"24","aa":"152","b":"09:12:04","ar":"I mål","aq":"05:00:00","Q":"6","ah":"05:53:18","am":"00:53:18","al":"53:18","aj":"06:02","ai":"9.95","ak":"306","K":"07:23:08","P":"02:23:08","O":"01:29:50","M":"06:13","L":"9.66","N":"304","ab":"08:29:20","ag":"03:29:20","af":"01:06:12","ad":"06:12","ac":"9.70","ae":"271","i":"09:42:02","n":"04:42:02","m":"01:12:42","k":"05:58","j":"10.07","l":"220","S":"11:15:41","X":"06:15:41","W":"01:33:39","U":"06:25","T":"9.36","V":"176","u":"12:13:26","z":"07:13:26","y":"57:45","w":"06:25","v":"9.35","x":"159","c":"13:16:32","h":"08:16:32","g":"01:03:06","e":"06:23","d":"9.41","f":"147","E":"14:12:04","J":"09:12:04","I":"55:32","G":"05:24","F":"11.13","H":"142"}],"9999991678885A0000149F0A":[{"a":"2015","B":"9999991678885A0000149F0A","A":"9999991678885A000021D34E","R":"Eriksson, Morgan (SWE)","ap":"1516","C":"M40","ao":"UL-90","D":"Torsby löparklubb","Y":"190","Z":"42","aa":"205","b":"09:08:10","ar":"I mål","aq":"05:00:00","ah":"05:48:03","am":"00:48:03","al":"48:03","aj":"05:27","ai":"11.04","ak":"157","K":"07:05:47","P":"02:05:47","O":"01:17:44","M":"05:23","L":"11.16","N":"152","ab":"08:07:56","ag":"03:07:56","af":"01:02:09","ad":"05:49","ac":"10.33","ae":"164","i":"09:26:15","n":"04:26:15","m":"01:18:19","k":"06:26","j":"9.35","l":"209","S":"11:01:26","X":"06:01:26","W":"01:35:11","U":"06:32","T":"9.20","V":"194","u":"12:04:45","z":"07:04:45","y":"01:03:19","w":"07:03","v":"8.53","x":"204","c":"13:14:48","h":"08:14:48","g":"01:10:03","e":"07:05","d":"8.48","f":"202","E":"14:08:10","J":"09:08:10","I":"53:22","G":"05:11","F":"11.58","H":"190"}],"9999991678885A000013890A":[{"a":"2015","B":"9999991678885A000013890A","A":"9999991678885A00001FC91E","R":"Hernwall, Patrik (SWE)","ap":"1424","C":"M45","ao":"UL-90","D":"Årsta","Y":"450","Z":"86","aa":"528","b":"11:11:54","ar":"I mål","aq":"05:00:00","ah":"06:04:15","am":"01:04:15","al":"01:04:15","aj":"07:17","ai":"8.26","ak":"671","K":"07:44:10","P":"02:44:10","O":"01:39:55","M":"06:55","L":"8.68","N":"633","ab":"08:59:30","ag":"03:59:30","af":"01:15:20","ad":"07:03","ac":"8.52","ae":"596","i":"10:25:29","n":"05:25:29","m":"01:25:59","k":"07:03","j":"8.51","l":"550","S":"12:22:08","X":"07:22:08","W":"01:56:39","U":"08:00","T":"7.51","V":"493","u":"13:34:58","z":"08:34:58","y":"01:12:50","w":"08:06","v":"7.41","x":"466","c":"14:57:16","h":"09:57:16","g":"01:22:18","e":"08:19","d":"7.22","f":"457","E":"16:11:54","J":"11:11:54","I":"01:14:38","G":"07:15","F":"8.28","H":"450"}],"99999916788859000003E60A":[{"a":"2015","B":"99999916788859000003E60A","A":"9999991678885A00001FC1B6","R":"Juujärvi, Leo (SWE)","ap":"1511","C":"M35","ao":"UL-90","D":"Dala Floda","Y":"607","Z":"124","aa":"721","b":"12:40:18","ar":"I mål","aq":"05:00:00","Q":"2","ah":"06:01:14","am":"01:01:14","al":"01:01:14","aj":"06:56","ai":"8.66","ak":"591","K":"07:40:25","P":"02:40:25","O":"01:39:11","M":"06:52","L":"8.75","N":"599","ab":"08:59:55","ag":"03:59:55","af":"01:19:30","ad":"07:26","ac":"8.07","ae":"600","i":"10:32:56","n":"05:32:56","m":"01:33:01","k":"07:38","j":"7.87","l":"582","S":"13:06:39","X":"08:06:39","W":"02:33:43","U":"10:32","T":"5.70","V":"628","u":"14:31:05","z":"09:31:05","y":"01:24:26","w":"09:23","v":"6.40","x":"613","c":"16:13:39","h":"11:13:39","g":"01:42:34","e":"10:22","d":"5.79","f":"609","E":"17:40:18","J":"12:40:18","I":"01:26:39","G":"08:25","F":"7.13","H":"607"}],"9999991678885A000013F90A":[{"a":"2015","B":"9999991678885A000013F90A","A":"9999991678885A000020A677","R":"Tronbøl, Morten (NOR)","ap":"1970","C":"M45","ao":"UL-90","D":"OPPSTAD I.L","ar":"Startade inte","aq":"05:00:00"}],"99999916788859000005810A":[{"a":"2015","B":"99999916788859000005810A","A":"9999991678885A0000202ADA","R":"Törngård, Maria (SWE)","ap":"3218","C":"W40","ao":"UL-90","D":"Hälle IF","Y":"123","Z":"30","aa":"736","b":"12:52:04","ar":"I mål","aq":"05:00:00","ah":"06:02:33","am":"01:02:33","al":"01:02:33","aj":"07:05","ai":"8.48","ak":"112","K":"07:38:10","P":"02:38:10","O":"01:35:37","M":"06:37","L":"9.07","N":"89","ab":"08:54:48","ag":"03:54:48","af":"01:16:38","ad":"07:10","ac":"8.38","ae":"82","i":"10:26:03","n":"05:26:03","m":"01:31:15","k":"07:29","j":"8.02","l":"86","S":"12:59:12","X":"07:59:12","W":"02:33:09","U":"10:30","T":"5.72","V":"107","u":"14:35:04","z":"09:35:04","y":"01:35:52","w":"10:40","v":"5.63","x":"115","c":"16:13:54","h":"11:13:54","g":"01:38:50","e":"09:59","d":"6.01","f":"115","E":"17:52:04","J":"12:52:04","I":"01:38:10","G":"09:32","F":"6.29","H":"123"},{"a":"2016","B":"99999916788859000005810A","A":"9999991678885A000023CA16","R":"Törngård, Maria (SWE)","ap":"3120","C":"W40","ao":"UL-90","D":"Hälle IF","Y":"80","Z":"25","aa":"500","b":"11:23:06","ar":"I mål","aq":"05:00:00"}],"99999916788859000007020A":[{"a":"2015","B":"99999916788859000007020A","A":"9999991678885A00001FAB8F","R":"Udd, Monika (SWE)","ap":"3219","C":"W65","ao":"UL-90","D":"IF Spartacus","ar":"Startade inte","aq":"05:00:00","Q":"2"}],"99999916788859000010770A":[{"a":"2016","B":"99999916788859000010770A","A":"9999991678885A000022476F","R":"Hammar, Jenny (SWE)","ap":"3075","C":"W35","ao":"UL-90","D":"Hallsbergs brottarklubb","Y":"117","Z":"15","aa":"661","b":"13:00:22","ar":"I mål","aq":"05:00:00"}],"9999991678885900000F200A":[{"a":"2016","B":"9999991678885900000F200A","A":"9999991678885A000026E118","R":"Löwendahl, Jonas (SWE)","ap":"1686","C":"M50","ao":"UL-90","D":"Linköpings skidklubb","Y":"202","Z":"14","aa":"230","b":"09:39:49","ar":"I mål","aq":"05:00:00","Q":"17"},{"a":"2019","B":"9999991678885900000F200A","A":"9999991678885B00002BAF1A","R":"Löwendahl, Jonas (SWE)","ap":"1044","C":"M50","ao":"UL-90","D":"Linköpings SK","Y":"555","Z":"63","aa":"702","b":"11:54:00","ar":"I mål","aq":"05:00:00","Q":"17","ah":"05:53:33","am":"00:53:33","al":"53:33","aj":"06:04","ai":"9.91","ak":"330","K":"07:24:44","P":"02:24:44","O":"01:31:11","M":"06:19","L":"9.52","N":"348","ab":"08:37:46","ag":"03:37:46","af":"01:13:02","ad":"06:50","ac":"8.79","ae":"349","i":"10:14:21","n":"05:14:21","m":"01:36:35","k":"07:55","j":"7.58","l":"402","S":"12:19:26","X":"07:19:26","W":"02:05:05","U":"08:35","T":"7.00","V":"420","u":"13:40:53","z":"08:40:53","y":"01:21:27","w":"09:03","v":"6.63","x":"440","c":"15:22:14","h":"10:22:14","g":"01:41:21","e":"10:15","d":"5.86","f":"485","E":"16:54:00","J":"11:54:00","I":"01:31:46","G":"08:55","F":"6.73","H":"555"}],"9999991678885900000D530A":[{"a":"2016","B":"9999991678885900000D530A","A":"9999991678885A0000250AA1","R":"Tuomainen, Tapio (SWE)","ap":"1532","C":"M50","ao":"UL-90","D":"Skärholmen","Y":"548","Z":"62","aa":"665","b":"13:08:47","ar":"I mål","aq":"05:00:00","Q":"9"}],"9999991678885900000BF80A":[{"a":"2016","B":"9999991678885900000BF80A","A":"9999991678885A000026E98E","R":"Wistrand, Anna (SWE)","ap":"3090","C":"W21","ao":"UL-90","D":"IFK MORA","Y":"47","Z":"18","aa":"336","b":"10:18:07","ar":"I mål","aq":"05:00:00","Q":"5"},{"a":"2017","B":"9999991678885900000BF80A","A":"9999991678885B00002ABC6F","R":"Wistrand, Anna (SWE)","ap":"3211","C":"W21","ao":"UL-90","D":"ASICS FrontRunner","ar":"Startade inte","aq":"05:00:00","Q":"5"}],"9999991678885A0001C21C0A":[{"a":"2017","B":"9999991678885A0001C21C0A","A":"9999991678885A000027215F","R":"Aho, Daniel (SWE)","ap":"1031","C":"M21","ao":"UL-90","D":"Västerås","Y":"541","Z":"106","aa":"661","b":"12:58:02","ar":"I mål","aq":"05:00:00","ah":"06:05:51","am":"01:05:51","al":"01:05:51","aj":"07:27","ai":"8.06","ak":"620","K":"07:49:26","P":"02:49:26","O":"01:43:35","M":"07:10","L":"8.38","N":"584","ab":"09:26:26","ag":"04:26:26","af":"01:37:00","ad":"09:04","ac":"6.62","ae":"589","i":"11:20:35","n":"06:20:35","m":"01:54:09","k":"09:22","j":"6.41","l":"621","S":"13:43:28","X":"08:43:28","W":"02:22:53","U":"09:48","T":"6.13","V":"585","u":"15:09:46","z":"10:09:46","y":"01:26:18","w":"09:36","v":"6.26","x":"576","c":"16:39:52","h":"11:39:52","g":"01:30:06","e":"09:07","d":"6.59","f":"550","E":"17:58:02","J":"12:58:02","I":"01:18:10","G":"07:36","F":"7.91","H":"541"}],"99999916788859000012990A":[{"a":"2017","B":"99999916788859000012990A","A":"9999991678885A0000272117","R":"Dahlén, Mats (SWE)","ap":"1018","C":"M35","ao":"UL-90","D":"Västerås","Y":"168","Z":"39","aa":"187","b":"09:27:39","ar":"I mål","aq":"05:00:00","ah":"05:49:41","am":"00:49:41","al":"49:41","aj":"05:38","ai":"10.68","ak":"150","K":"07:12:29","P":"02:12:29","O":"01:22:48","M":"05:44","L":"10.48","N":"133","ab":"08:21:02","ag":"03:21:02","af":"01:08:33","ad":"06:25","ac":"9.37","ae":"146","i":"09:36:00","n":"04:36:00","m":"01:14:58","k":"06:09","j":"9.76","l":"139","S":"11:11:57","X":"06:11:57","W":"01:35:57","U":"06:35","T":"9.13","V":"145","u":"12:17:30","z":"07:17:30","y":"01:05:33","w":"07:17","v":"8.24","x":"159","c":"13:26:20","h":"08:26:20","g":"01:08:50","e":"06:58","d":"8.63","f":"159","E":"14:27:39","J":"09:27:39","I":"01:01:19","G":"05:58","F":"10.08","H":"168"},{"a":"2018","B":"99999916788859000012990A","A":"9999991678885B00002AEF3A","R":"Dahlén, Mats (SWE)","ap":"1049","C":"M35","ao":"UL-90","Y":"79","Z":"18","aa":"90","b":"08:40:53","ar":"I mål","aq":"05:00:00","ah":"05:49:41","am":"00:49:41","al":"49:41","aj":"05:38","ai":"10.68","ak":"144","K":"07:01:25","P":"02:01:25","O":"01:11:44","M":"04:58","L":"12.09","N":"82","ab":"07:59:48","ag":"02:59:48","af":"58:23","ad":"05:28","ac":"11.00","ae":"74","i":"09:10:21","n":"04:10:21","m":"01:10:33","k":"05:47","j":"10.38","l":"74","S":"10:38:35","X":"05:38:35","W":"01:28:14","U":"06:03","T":"9.93","V":"68","u":"11:38:19","z":"06:38:19","y":"59:44","w":"06:39","v":"9.04","x":"70","c":"12:43:25","h":"07:43:25","g":"01:05:06","e":"06:35","d":"9.12","f":"73","E":"13:40:53","J":"08:40:53","I":"57:28","G":"05:35","F":"10.75","H":"79"},{"a":"2019","B":"99999916788859000012990A","A":"9999991678886900004CFFD0","R":"Dahlén, Mats (SWE)","ap":"1663","C":"M40","ao":"UL-90","D":"Västerås","Y":"347","Z":"76","aa":"422","b":"10:42:19","ar":"I mål","aq":"05:00:00","ah":"05:46:27","am":"00:46:27","al":"46:27","aj":"05:16","ai":"11.42","ak":"102","K":"07:00:57","P":"02:00:57","O":"01:14:30","M":"05:10","L":"11.65","N":"85","ab":"08:04:37","ag":"03:04:37","af":"01:03:40","ad":"05:58","ac":"10.08","ae":"93","i":"09:27:16","n":"04:27:16","m":"01:22:39","k":"06:47","j":"8.86","l":"130","S":"11:21:56","X":"06:21:56","W":"01:54:40","U":"07:52","T":"7.64","V":"200","u":"12:46:51","z":"07:46:51","y":"01:24:55","w":"09:27","v":"6.36","x":"267","c":"14:25:41","h":"09:25:41","g":"01:38:50","e":"09:59","d":"6.01","f":"321","E":"15:42:19","J":"10:42:19","I":"01:16:38","G":"07:27","F":"8.06","H":"347"}],"9999991678885B0001C4080A":[{"a":"2017","B":"9999991678885B0001C4080A","A":"9999991678885B00002AB496","R":"Ekelund, Sara (SWE)","ap":"3195","C":"W21","ao":"UL-90","D":"Team Nordic Trail (slögruppen)","Y":"129","Z":"32","aa":"685","b":"13:15:17","ar":"I mål","aq":"05:00:00","ah":"06:12:52","am":"01:12:52","al":"01:12:52","aj":"08:15","ai":"7.28","ak":"179","K":"08:05:24","P":"03:05:24","O":"01:52:32","M":"07:47","L":"7.71","N":"164","ab":"09:43:32","ag":"04:43:32","af":"01:38:08","ad":"09:11","ac":"6.54","ae":"150","i":"11:27:15","n":"06:27:15","m":"01:43:43","k":"08:31","j":"7.06","l":"145","S":"13:45:42","X":"08:45:42","W":"02:18:27","U":"09:29","T":"6.33","V":"133","u":"15:08:07","z":"10:08:07","y":"01:22:25","w":"09:10","v":"6.55","x":"125","c":"16:47:18","h":"11:47:18","g":"01:39:11","e":"10:02","d":"5.99","f":"127","E":"18:15:17","J":"13:15:17","I":"01:27:59","G":"08:33","F":"7.02","H":"129"}],"9999991678885900000D730A":[{"a":"2018","B":"9999991678885900000D730A","A":"9999991678885B00002AFA2E","R":"Innala, Richard (SWE)","ap":"1088","C":"M35","ao":"UL-90","D":"Åkersberga triathlonföreining","Y":"718","Z":"132","aa":"921","b":"14:13:17","ar":"I mål","aq":"05:00:00","Q":"5","ah":"06:12:09","am":"01:12:09","al":"01:12:09","aj":"08:10","ai":"7.35","ak":"770","K":"07:59:52","P":"02:59:52","O":"01:47:43","M":"07:27","L":"8.05","N":"735","ab":"09:44:57","ag":"04:44:57","af":"01:45:05","ad":"09:50","ac":"6.11","ae":"764","i":"11:47:38","n":"06:47:38","m":"02:02:41","k":"10:04","j":"5.97","l":"770","S":"14:20:23","X":"09:20:23","W":"02:32:45","U":"10:28","T":"5.73","V":"739","u":"16:03:40","z":"11:03:40","y":"01:43:17","w":"11:29","v":"5.23","x":"733","c":"17:43:42","h":"12:43:42","g":"01:40:02","e":"10:07","d":"5.94","f":"723","E":"19:13:17","J":"14:13:17","I":"01:29:35","G":"08:42","F":"6.90","H":"718"}],"9999991678885B0001C3760A":[{"a":"2018","B":"9999991678885B0001C3760A","A":"9999991678885F000031F75E","R":"Rune, Emil (SWE)","ap":"1906","C":"H19-20","ao":"UL-90","Y":"569","Z":"3","aa":"717","b":"12:20:41","ar":"I mål","aq":"05:00:00","Q":"2","ah":"05:51:17","am":"00:51:17","al":"51:17","aj":"05:49","ai":"10.34","ak":"178","K":"07:14:05","P":"02:14:05","O":"01:22:48","M":"05:44","L":"10.48","N":"191","ab":"08:26:22","ag":"03:26:22","af":"01:12:17","ad":"06:46","ac":"8.88","ae":"227","i":"10:12:17","n":"05:12:17","m":"01:45:55","k":"08:41","j":"6.91","l":"375","S":"12:25:47","X":"07:25:47","W":"02:13:30","U":"09:09","T":"6.56","V":"446","u":"13:51:33","z":"08:51:33","y":"01:25:46","w":"09:32","v":"6.30","x":"474","c":"15:37:59","h":"10:37:59","g":"01:46:26","e":"10:46","d":"5.58","f":"518","E":"17:20:41","J":"12:20:41","I":"01:42:42","G":"09:59","F":"6.02","H":"569"},{"a":"2019","B":"9999991678885B0001C3760A","A":"9999991678886900004F9303","R":"Rune, Emil (SWE)","ap":"1729","C":"M21","ao":"UL-90","D":"Jönköping","Y":"357","Z":"83","aa":"441","b":"10:48:06","ar":"I mål","aq":"05:00:00","Q":"2","ah":"05:58:44","am":"00:58:44","al":"58:44","aj":"06:39","ai":"9.03","ak":"530","K":"07:42:13","P":"02:42:13","O":"01:43:29","M":"07:10","L":"8.38","N":"575","ab":"09:02:57","ag":"04:02:57","af":"01:20:44","ad":"07:33","ac":"7.95","ae":"547","i":"10:27:27","n":"05:27:27","m":"01:24:30","k":"06:56","j":"8.66","l":"482","S":"12:22:58","X":"07:22:58","W":"01:55:31","U":"07:55","T":"7.58","V":"436","u":"13:31:24","z":"08:31:24","y":"01:08:26","w":"07:37","v":"7.89","x":"402","c":"14:48:08","h":"09:48:08","g":"01:16:44","e":"07:46","d":"7.74","f":"385","E":"15:48:06","J":"10:48:06","I":"59:58","G":"05:50","F":"10.30","H":"357"}],"999999167888620001C5680A":[{"a":"2019","B":"999999167888620001C5680A","A":"999999167888620000351B39","R":"Andersson, Tobias (SWE)","ap":"1294","C":"M35","ao":"UL-90","D":"Corpus","Y":"192","Z":"39","aa":"221","b":"09:29:27","ar":"I mål","aq":"05:00:00","ah":"05:50:28","am":"00:50:28","al":"50:28","aj":"05:43","ai":"10.51","ak":"227","K":"07:15:58","P":"02:15:58","O":"01:25:30","M":"05:55","L":"10.15","N":"221","ab":"08:24:16","ag":"03:24:16","af":"01:08:18","ad":"06:23","ac":"9.40","ae":"216","i":"09:38:05","n":"04:38:05","m":"01:13:49","k":"06:04","j":"9.92","l":"190","S":"11:15:34","X":"06:15:34","W":"01:37:29","U":"06:41","T":"8.99","V":"172","u":"12:17:10","z":"07:17:10","y":"01:01:36","w":"06:51","v":"8.77","x":"167","c":"13:31:44","h":"08:31:44","g":"01:14:34","e":"07:32","d":"7.97","f":"184","E":"14:29:27","J":"09:29:27","I":"57:43","G":"05:37","F":"10.71","H":"192"}],"9999991678885B0001C3B20A":[{"a":"2019","B":"9999991678885B0001C3B20A","A":"99999916788868000041493B","R":"Nyberg, Sonny (SWE)","ap":"1499","C":"M21","ao":"UL-90","D":"Team Nyberg","Y":"448","Z":"109","aa":"565","b":"11:19:57","ar":"I mål","aq":"05:00:00","Q":"2","ah":"06:05:24","am":"01:05:24","al":"01:05:24","aj":"07:24","ai":"8.11","ak":"745","K":"07:53:12","P":"02:53:12","O":"01:47:48","M":"07:28","L":"8.05","N":"701","ab":"09:20:44","ag":"04:20:44","af":"01:27:32","ad":"08:11","ac":"7.33","ae":"681","i":"10:48:49","n":"05:48:49","m":"01:28:05","k":"07:14","j":"8.31","l":"615","S":"12:44:16","X":"07:44:16","W":"01:55:27","U":"07:55","T":"7.59","V":"534","u":"14:00:40","z":"09:00:40","y":"01:16:24","w":"08:30","v":"7.07","x":"510","c":"15:14:14","h":"10:14:14","g":"01:13:34","e":"07:26","d":"8.07","f":"466","E":"16:19:57","J":"11:19:57","I":"01:05:43","G":"06:23","F":"9.40","H":"448"},{"a":"2022","B":"9999991678885B0001C3B20A","A":"9999991678887600008735B7","R":"Nyberg, Sonny (SWE)","ap":"1081","C":"M35","ao":"UL90","D":"Team Nyberg","Y":"265","Z":"40","aa":"340","b":"10:44:01","ar":"I mål","aq":"05:00:00","Q":"2","ah":"05:53:53","am":"00:53:53","al":"53:53","aj":"06:06","ai":"9.84","ak":"250","K":"07:23:36","P":"02:23:36","O":"01:29:43","M":"06:13","L":"9.67","N":"224","ab":"08:39:37","ag":"03:39:37","af":"01:16:01","ad":"07:07","ac":"8.44","ae":"248","i":"10:07:36","n":"05:07:36","m":"01:27:59","k":"07:13","j":"8.32","l":"258","S":"11:54:31","X":"06:54:31","W":"01:46:55","U":"07:20","T":"8.19","V":"240","u":"13:12:12","z":"08:12:12","y":"01:17:41","w":"08:38","v":"6.95","x":"258","c":"14:35:46","h":"09:35:46","g":"01:23:34","e":"08:27","d":"7.11","f":"260","E":"15:44:01","J":"10:44:01","I":"01:08:15","G":"06:38","F":"9.05","H":"265"}],"9999991678885900000E2C0A":[{"a":"2022","B":"9999991678885900000E2C0A","A":"HCH8NDMR9E66C2","R":"Berglund, Dan (SWE)","ap":"1734","C":"M45","ao":"UL90","D":"RÅÅ","Y":"176","Z":"37","aa":"217","b":"09:55:42","ar":"I mål","aq":"05:00:00","Q":"2","ah":"05:49:36","am":"00:49:36","al":"49:36","aj":"05:37","ai":"10.69","ak":"110","K":"07:21:59","P":"02:21:59","O":"01:32:23","M":"06:24","L":"9.39","N":"194","ab":"08:35:18","ag":"03:35:18","af":"01:13:19","ad":"06:52","ac":"8.76","ae":"210","i":"09:53:24","n":"04:53:24","m":"01:18:06","k":"06:25","j":"9.37","l":"195","S":"11:33:52","X":"06:33:52","W":"01:40:28","U":"06:53","T":"8.72","V":"178","u":"12:36:35","z":"07:36:35","y":"01:02:43","w":"06:59","v":"8.61","x":"166","c":"13:47:19","h":"08:47:19","g":"01:10:44","e":"07:09","d":"8.40","f":"157","E":"14:55:42","J":"09:55:42","I":"01:08:23","G":"06:39","F":"9.04","H":"176"},{"a":"2024","B":"9999991678885900000E2C0A","A":"HCH8NDMRA199A5","R":"Berglund, Dan (SWE)","ap":"2191","C":"M45","ao":"UL90","D":"Rexel","Y":"278","Z":"49","aa":"339","b":"10:50:48","ar":"I mål","aq":"05:00:00","Q":"2","o":"05:29:28","t":"00:29:28","s":"29:28","q":"08:56","p":"6.72","r":"373","ah":"06:18:55","am":"01:18:55","al":"49:27","aj":"06:33","ai":"9.16","ak":"343","K":"07:55:20","P":"02:55:20","O":"01:36:25","M":"06:38","L":"9.05","N":"340","ab":"09:14:03","ag":"04:14:03","af":"01:18:43","ad":"07:08","ac":"8.42","ae":"337","i":"10:44:26","n":"05:44:26","m":"01:30:23","k":"07:20","j":"8.20","l":"344","S":"12:29:18","X":"07:29:18","W":"01:44:52","U":"07:08","T":"8.42","V":"301","u":"13:39:55","z":"08:39:55","y":"01:10:37","w":"07:42","v":"7.80","x":"301","c":"14:50:45","h":"09:50:45","g":"01:10:50","e":"06:59","d":"8.60","f":"286","E":"15:50:48","J":"10:50:48","I":"01:00:03","G":"06:46","F":"8.88","H":"278"}],"9999991678885900000E120A":[{"a":"2022","B":"9999991678885900000E120A","A":"HCH8NDMR9F96AA","R":"Bäck, Åsa (SWE)","ap":"3393","C":"W50","ao":"UL90","D":"Himmeta IF","Y":"21","Z":"5","aa":"104","b":"09:04:47","ar":"I mål","aq":"05:00:00","Q":"9","ah":"05:47:54","am":"00:47:54","al":"47:54","aj":"05:26","ai":"11.07","ak":"22","K":"07:13:41","P":"02:13:41","O":"01:25:47","M":"05:56","L":"10.11","N":"29","ab":"08:21:10","ag":"03:21:10","af":"01:07:29","ad":"06:19","ac":"9.51","ae":"26","i":"09:34:45","n":"04:34:45","m":"01:13:35","k":"06:02","j":"9.95","l":"22","S":"11:06:26","X":"06:06:26","W":"01:31:41","U":"06:17","T":"9.55","V":"20","u":"12:05:44","z":"07:05:44","y":"59:18","w":"06:36","v":"9.11","x":"20","c":"13:09:24","h":"08:09:24","g":"01:03:40","e":"06:26","d":"9.33","f":"20","E":"14:04:47","J":"09:04:47","I":"55:23","G":"05:23","F":"11.16","H":"21"},{"a":"2023","B":"9999991678885900000E120A","A":"HCH8NDMRA06992","R":"Bäck, Åsa (SWE)","ap":"W1153","C":"W50","ao":"UL90","D":"Himmeta IF","Y":"22","Z":"1","aa":"120","b":"09:45:04","ar":"I mål","aq":"05:00:00","Q":"9","o":"05:21:19","t":"00:21:19","s":"21:19","q":"06:28","p":"9.29","r":"22","ah":"06:06:07","am":"01:06:07","al":"44:48","aj":"05:57","ai":"10.11","ak":"24","K":"07:33:04","P":"02:33:04","O":"01:26:57","M":"05:59","L":"10.04","N":"27","ab":"08:44:26","ag":"03:44:26","af":"01:11:22","ad":"06:28","ac":"9.29","ae":"29","i":"10:04:53","n":"05:04:53","m":"01:20:27","k":"06:31","j":"9.23","l":"27","S":"11:40:07","X":"06:40:07","W":"01:35:14","U":"06:25","T":"9.37","V":"25","u":"12:41:23","z":"07:41:23","y":"01:01:16","w":"06:40","v":"9.01","x":"23","c":"13:48:56","h":"08:48:56","g":"01:07:33","e":"06:40","d":"9.02","f":"23","E":"14:45:04","J":"09:45:04","I":"56:08","G":"06:11","F":"9.71","H":"22"},{"a":"2024","B":"9999991678885900000E120A","A":"HCH8NDMRA331A5","R":"Bäck, Åsa (SWE)","ap":"1078","C":"W50","ao":"UL90","D":"Himmeta IF","Y":"27","Z":"3","aa":"179","b":"09:49:41","ar":"I mål","aq":"05:00:00","Q":"9","o":"05:22:39","t":"00:22:39","s":"22:39","q":"06:52","p":"8.74","r":"20","ah":"06:06:22","am":"01:06:22","al":"43:43","aj":"05:48","ai":"10.36","ak":"24","K":"07:33:17","P":"02:33:17","O":"01:26:55","M":"05:59","L":"10.04","N":"26","ab":"08:44:01","ag":"03:44:01","af":"01:10:44","ad":"06:25","ac":"9.37","ae":"27","i":"10:01:55","n":"05:01:55","m":"01:17:54","k":"06:19","j":"9.51","l":"24","S":"11:32:49","X":"06:32:49","W":"01:30:54","U":"06:11","T":"9.72","V":"24","u":"12:35:45","z":"07:35:45","y":"01:02:56","w":"06:52","v":"8.75","x":"23","c":"13:47:29","h":"08:47:29","g":"01:11:44","e":"07:05","d":"8.49","f":"26","E":"14:49:41","J":"09:49:41","I":"01:02:12","G":"07:00","F":"8.57","H":"27"},{"a":"2025","B":"9999991678885900000E120A","A":"HCH8NDMRA5767F","R":"Bäck, Åsa (SWE)","ap":"1072","C":"W50","ao":"UL90","D":"Himmeta IF","Y":"29","Z":"3","aa":"155","b":"09:27:58","an":"9.68","ar":"I mål","aq":"05:00:00","Q":"9","o":"05:21:45","t":"00:21:45","s":"21:45","q":"06:36","p":"9.11","r":"22","ah":"06:05:28","am":"01:05:28","al":"43:43","aj":"05:48","ai":"10.36","ak":"24","K":"07:32:45","P":"02:32:45","O":"01:27:17","M":"06:02","L":"9.97","N":"28","ab":"08:41:54","ag":"03:41:54","af":"01:09:09","ad":"06:15","ac":"9.61","ae":"29","i":"09:58:25","n":"04:58:25","m":"01:16:31","k":"06:13","j":"9.65","l":"27","S":"11:29:15","X":"06:29:15","W":"01:30:50","U":"06:10","T":"9.73","V":"28","u":"12:27:26","z":"07:27:26","y":"58:11","w":"06:22","v":"9.44","x":"29","c":"13:31:00","h":"08:31:00","g":"01:03:34","e":"06:16","d":"9.60","f":"28","E":"14:27:58","J":"09:27:58","I":"03:05","G":"05:09","F":"11.63","H":"29"}],"999999167888700001C66C0A":[{"a":"2022","B":"999999167888700001C66C0A","A":"99999916788876000088B1E7","R":"Nordlander, Vera (SWE)","ap":"3117","C":"W45","ao":"UL90","D":"BRO","ar":"Startade inte","aq":"05:00:00"},{"a":"2023","B":"999999167888700001C66C0A","A":"HCH8NDMRA003EC","R":"Nordlander, Vera (SWE)","ap":"W1062","C":"W45","ao":"UL90","D":"BRO","Y":"219","Z":"48","aa":"854","b":"14:04:10","ar":"I mål","aq":"05:00:00","o":"05:34:59","t":"00:34:59","s":"34:59","q":"10:37","p":"5.66","r":"269","ah":"06:49:42","am":"01:49:42","al":"01:14:43","aj":"09:54","ai":"6.06","ak":"297","K":"08:48:03","P":"03:48:03","O":"01:58:21","M":"08:09","L":"7.38","N":"270","ab":"10:22:56","ag":"05:22:56","af":"01:34:53","ad":"08:36","ac":"6.99","ae":"239","i":"12:11:05","n":"07:11:05","m":"01:48:09","k":"08:45","j":"6.87","l":"237","S":"14:37:00","X":"09:37:00","W":"02:25:55","U":"09:49","T":"6.12","V":"228","u":"16:12:31","z":"11:12:31","y":"01:35:31","w":"10:23","v":"5.78","x":"230","c":"17:50:07","h":"12:50:07","g":"01:37:36","e":"09:37","d":"6.24","f":"228","E":"19:04:10","J":"14:04:10","I":"01:14:03","G":"08:10","F":"7.36","H":"219"},{"a":"2025","B":"999999167888700001C66C0A","A":"HCH8NDMRA51869","R":"Nordlander, Vera (SWE)","ap":"1418","C":"W50","ao":"UL90","D":"BRO","Y":"312","Z":"34","aa":"1221","b":"14:00:36","an":"6.54","ar":"I mål","aq":"05:00:00","o":"05:32:35","t":"00:32:35","s":"32:35","q":"09:53","p":"6.08","r":"226","ah":"06:33:25","am":"01:33:25","al":"01:00:50","aj":"08:04","ai":"7.45","ak":"253","K":"08:40:01","P":"03:40:01","O":"02:06:36","M":"08:44","L":"6.87","N":"322","ab":"10:30:10","ag":"05:30:10","af":"01:50:09","ad":"09:58","ac":"6.03","ae":"358","i":"12:33:52","n":"07:33:52","m":"02:03:42","k":"10:03","j":"5.97","l":"378","S":"14:50:59","X":"09:50:59","W":"02:17:07","U":"09:19","T":"6.45","V":"349","u":"16:13:04","z":"11:13:04","y":"01:22:05","w":"08:58","v":"6.70","x":"331","c":"17:46:10","h":"12:46:10","g":"01:33:06","e":"09:10","d":"6.55","f":"317","E":"19:00:36","J":"14:00:36","I":"03:56","G":"06:34","F":"9.14","H":"312"}],"999999167888760001C7A30A":[{"a":"2022","B":"999999167888760001C7A30A","A":"9999991678887600009A2A89","R":"Friborg Prando, Carin (SWE)","ap":"3172","C":"W21","ao":"UL90","D":"Arvidsjaur","ar":"Startade inte","aq":"05:00:00"}],"9999991678885900000E3E0A":[{"a":"2022","B":"9999991678885900000E3E0A","A":"HCH8NDMR9F8CD4","R":"Tigér, Johan (SWE)","ap":"1970","C":"M40","ao":"UL90","D":"Göteborg","ar":"Startade inte","aq":"05:00:00","Q":"1"}],"BH28NDMR1C90D0A":[{"a":"2023","B":"BH28NDMR1C90D0A","A":"HCH8NDMR9FFDEF","R":"Landström, Anton (SWE)","ap":"M1099","C":"M21","ao":"UL90","D":"Timmernabben","Y":"440","Z":"126","aa":"560","b":"12:33:38","ar":"I mål","aq":"05:00:00","o":"05:27:54","t":"00:27:54","s":"27:54","q":"08:28","p":"7.10","r":"296","ah":"06:17:54","am":"01:17:54","al":"50:00","aj":"06:38","ai":"9.06","ak":"260","K":"07:51:34","P":"02:51:34","O":"01:33:40","M":"06:27","L":"9.32","N":"255","ab":"09:08:34","ag":"04:08:34","af":"01:17:00","ad":"06:59","ac":"8.61","ae":"260","i":"10:47:11","n":"05:47:11","m":"01:38:37","k":"07:59","j":"7.53","l":"294","S":"13:28:46","X":"08:28:46","W":"02:41:35","U":"10:52","T":"5.52","V":"437","u":"14:57:16","z":"09:57:16","y":"01:28:30","w":"09:38","v":"6.24","x":"459","c":"16:20:40","h":"11:20:40","g":"01:23:24","e":"08:14","d":"7.30","f":"443","E":"17:33:38","J":"12:33:38","I":"01:12:58","G":"08:03","F":"7.47","H":"440"}],"HCH8NDMR1C9EC0A":[{"a":"2024","B":"HCH8NDMR1C9EC0A","A":"HCH8NDMRA2DC89","R":"Björklund, Felix (SWE)","ap":"2656","C":"M21","ao":"UL90","D":"KARLSTAD","Y":"198","Z":"57","aa":"240","b":"10:17:47","ar":"I mål","aq":"05:00:00","Q":"1","o":"05:31:28","t":"00:31:28","s":"31:28","q":"09:33","p":"6.29","r":"485","ah":"06:20:07","am":"01:20:07","al":"48:39","aj":"06:27","ai":"9.31","ak":"386","K":"07:52:10","P":"02:52:10","O":"01:32:03","M":"06:20","L":"9.48","N":"298","ab":"09:01:33","ag":"04:01:33","af":"01:09:23","ad":"06:17","ac":"9.55","ae":"255","i":"10:24:30","n":"05:24:30","m":"01:22:57","k":"06:43","j":"8.93","l":"245","S":"12:06:47","X":"07:06:47","W":"01:42:17","U":"06:57","T":"8.64","V":"229","u":"13:14:36","z":"08:14:36","y":"01:07:49","w":"07:24","v":"8.12","x":"231","c":"14:25:43","h":"09:25:43","g":"01:11:07","e":"07:01","d":"8.56","f":"217","E":"15:17:47","J":"10:17:47","I":"52:04","G":"05:52","F":"10.24","H":"198"}],"HCH8NDMR1C9150A":[{"a":"2024","B":"HCH8NDMR1C9150A","A":"HCH8NDMRA189E1","R":"Enocksson, Jon (SWE)","ap":"2050","C":"M50","ao":"UL90","D":"Spring Lola","Y":"470","Z":"44","aa":"585","b":"12:03:11","ar":"I mål","aq":"05:00:00","o":"05:33:05","t":"00:33:05","s":"33:05","q":"10:02","p":"5.99","r":"571","ah":"06:31:40","am":"01:31:40","al":"58:35","aj":"07:46","ai":"7.73","ak":"646","K":"08:29:05","P":"03:29:05","O":"01:57:25","M":"08:05","L":"7.43","N":"705","ab":"09:58:19","ag":"04:58:19","af":"01:29:14","ad":"08:05","ac":"7.43","ae":"673","i":"11:29:08","n":"06:29:08","m":"01:30:49","k":"07:22","j":"8.16","l":"611","S":"13:25:42","X":"08:25:42","W":"01:56:34","U":"07:55","T":"7.58","V":"546","u":"14:38:52","z":"09:38:52","y":"01:13:10","w":"07:59","v":"7.52","x":"509","c":"15:56:23","h":"10:56:23","g":"01:17:31","e":"07:39","d":"7.86","f":"482","E":"17:03:11","J":"12:03:11","I":"01:06:48","G":"07:31","F":"7.98","H":"470"}],"HCH8NDMR1CA6A0A":[{"a":"2024","B":"HCH8NDMR1CA6A0A","A":"HCH8NDMRA323AE","R":"Farås, Simon (SWE)","ap":"2878","C":"M40","ao":"UL90","D":"FALUN","Y":"157","Z":"36","aa":"184","b":"09:51:19","ar":"I mål","aq":"05:00:00","o":"05:33:16","t":"00:33:16","s":"33:16","q":"10:05","p":"5.95","r":"594","ah":"06:25:15","am":"01:25:15","al":"51:59","aj":"06:54","ai":"8.72","ak":"500","K":"07:58:22","P":"02:58:22","O":"01:33:07","M":"06:24","L":"9.38","N":"389","ab":"09:11:06","ag":"04:11:06","af":"01:12:44","ad":"06:35","ac":"9.11","ae":"323","i":"10:30:49","n":"05:30:49","m":"01:19:43","k":"06:28","j":"9.30","l":"275","S":"12:07:59","X":"07:07:59","W":"01:37:10","U":"06:36","T":"9.09","V":"236","u":"13:02:36","z":"08:02:36","y":"54:37","w":"05:58","v":"10.08","x":"195","c":"14:00:58","h":"09:00:58","g":"58:22","e":"05:46","d":"10.44","f":"174","E":"14:51:19","J":"09:51:19","I":"50:21","G":"05:40","F":"10.59","H":"157"}],"HCH8NDMR1CA550A":[{"a":"2024","B":"HCH8NDMR1CA550A","A":"HCH8NDMRA2E6E5","R":"Färén, Olav (SWE)","ap":"2679","C":"M21","ao":"UL90","D":"GÖTENE","Y":"724","Z":"214","aa":"961","b":"13:48:56","ar":"I mål","aq":"05:00:00","o":"05:34:21","t":"00:34:21","s":"34:21","q":"10:25","p":"5.77","r":"677","ah":"06:38:27","am":"01:38:27","al":"01:04:06","aj":"08:30","ai":"7.07","ak":"787","K":"08:42:49","P":"03:42:49","O":"02:04:22","M":"08:33","L":"7.02","N":"881","ab":"10:22:02","ag":"05:22:02","af":"01:39:13","ad":"08:59","ac":"6.68","ae":"855","i":"12:14:50","n":"07:14:50","m":"01:52:48","k":"09:09","j":"6.57","l":"840","S":"14:34:18","X":"09:34:18","W":"02:19:28","U":"09:29","T":"6.34","V":"805","u":"16:03:19","z":"11:03:19","y":"01:29:01","w":"09:43","v":"6.18","x":"781","c":"17:38:39","h":"12:38:39","g":"01:35:20","e":"09:24","d":"6.39","f":"755","E":"18:48:56","J":"13:48:56","I":"01:10:17","G":"07:55","F":"7.59","H":"724"}],"99999916788859000004D10A":[{"a":"2024","B":"99999916788859000004D10A","A":"HCH8NDMRA32A85","R":"Kyllerman, Christian (SWE)","ap":"2960","C":"M45","ao":"UL90","D":"Evalds IF","Y":"242","Z":"41","aa":"295","b":"10:38:51","ar":"I mål","aq":"05:00:00","Q":"5","o":"05:24:57","t":"00:24:57","s":"24:57","q":"07:34","p":"7.94","r":"178","ah":"06:12:38","am":"01:12:38","al":"47:41","aj":"06:19","ai":"9.50","ak":"221","K":"07:51:31","P":"02:51:31","O":"01:38:53","M":"06:48","L":"8.83","N":"288","ab":"09:05:16","ag":"04:05:16","af":"01:13:45","ad":"06:41","ac":"8.99","ae":"280","i":"10:29:29","n":"05:29:29","m":"01:24:13","k":"06:50","j":"8.80","l":"268","S":"12:18:26","X":"07:18:26","W":"01:48:57","U":"07:24","T":"8.11","V":"270","u":"13:30:17","z":"08:30:17","y":"01:11:51","w":"07:50","v":"7.66","x":"273","c":"14:42:40","h":"09:42:40","g":"01:12:23","e":"07:08","d":"8.41","f":"260","E":"15:38:51","J":"10:38:51","I":"56:11","G":"06:20","F":"9.49","H":"242"},{"a":"2025","B":"99999916788859000004D10A","A":"HCH8NDMRA52908","R":"Kyllerman, Christian (SWE)","ap":"3250","C":"M45","ao":"UL90","D":"Evalds IF","Y":"173","Z":"31","aa":"215","b":"09:47:13","an":"9.37","ar":"I mål","aq":"05:00:00","Q":"5","o":"05:24:40","t":"00:24:40","s":"24:40","q":"07:29","p":"8.03","r":"252","ah":"06:11:08","am":"01:11:08","al":"46:28","aj":"06:10","ai":"9.75","ak":"275","K":"07:41:34","P":"02:41:34","O":"01:30:26","M":"06:15","L":"9.62","N":"294","ab":"08:52:03","ag":"03:52:03","af":"01:10:29","ad":"06:23","ac":"9.42","ae":"266","i":"10:11:15","n":"05:11:15","m":"01:19:12","k":"06:27","j":"9.33","l":"243","S":"11:51:00","X":"06:51:00","W":"01:39:45","U":"06:47","T":"8.86","V":"228","u":"12:50:39","z":"07:50:39","y":"59:39","w":"06:31","v":"9.21","x":"207","c":"13:53:37","h":"08:53:37","g":"01:02:58","e":"06:12","d":"9.69","f":"185","E":"14:47:13","J":"09:47:13","I":"02:47","G":"04:39","F":"12.93","H":"173"}],"HCH8NDMR1C9C70A":[{"a":"2024","B":"HCH8NDMR1C9C70A","A":"HCH8NDMRA1908A","R":"Norberg, Björn (SWE)","ap":"2078","C":"M55","ao":"UL90","D":"Run for Hope Umeå","Y":"628","Z":"32","aa":"810","b":"13:04:27","ar":"I mål","aq":"05:00:00","o":"05:34:37","t":"00:34:37","s":"34:37","q":"10:30","p":"5.72","r":"697","ah":"06:37:04","am":"01:37:04","al":"01:02:27","aj":"08:17","ai":"7.25","ak":"760","K":"08:30:41","P":"03:30:41","O":"01:53:37","M":"07:49","L":"7.68","N":"730","ab":"10:02:43","ag":"05:02:43","af":"01:32:02","ad":"08:20","ac":"7.20","ae":"702","i":"11:43:07","n":"06:43:07","m":"01:40:24","k":"08:08","j":"7.38","l":"693","S":"13:49:36","X":"08:49:36","W":"02:06:29","U":"08:36","T":"6.98","V":"650","u":"15:15:00","z":"10:15:00","y":"01:25:24","w":"09:19","v":"6.45","x":"638","c":"16:45:37","h":"11:45:37","g":"01:30:37","e":"08:56","d":"6.72","f":"631","E":"18:04:27","J":"13:04:27","I":"01:18:50","G":"08:53","F":"6.77","H":"628"}],"HCH8NDMR1CA6C0A":[{"a":"2024","B":"HCH8NDMR1CA6C0A","A":"HCH8NDMRA32877","R":"Terserus, Jill (SWE)","ap":"1410","C":"W55","ao":"UL90","D":"BERGEN","Y":"105","Z":"4","aa":"469","b":"11:35:26","ar":"I mål","aq":"05:00:00","o":"05:36:02","t":"00:36:02","s":"36:02","q":"10:56","p":"5.50","r":"300","ah":"06:33:12","am":"01:33:12","al":"57:10","aj":"07:35","ai":"7.93","ak":"224","K":"08:21:20","P":"03:21:20","O":"01:48:08","M":"07:26","L":"8.07","N":"159","ab":"09:45:58","ag":"04:45:58","af":"01:24:38","ad":"07:40","ac":"7.83","ae":"136","i":"11:18:31","n":"06:18:31","m":"01:32:33","k":"07:30","j":"8.01","l":"124","S":"13:17:34","X":"08:17:34","W":"01:59:03","U":"08:06","T":"7.42","V":"121","u":"14:26:36","z":"09:26:36","y":"01:09:02","w":"07:32","v":"7.97","x":"111","c":"15:35:45","h":"10:35:45","g":"01:09:09","e":"06:49","d":"8.81","f":"104","E":"16:35:26","J":"11:35:26","I":"59:41","G":"06:43","F":"8.94","H":"105"}],"9999991678885900000F360A":[{"a":"2025","B":"9999991678885900000F360A","A":"HCH8NDMRA3F75F","R":"Axelsson, Martin (SWE)","ap":"2353","C":"M35","ao":"UL90","D":"OK Nackhe","Y":"242","Z":"47","aa":"300","b":"10:18:51","an":"8.89","ar":"I mål","aq":"05:00:00","Q":"2","o":"05:22:00","t":"00:22:00","s":"22:00","q":"06:40","p":"9.00","r":"120","ah":"06:05:28","am":"01:05:28","al":"43:28","aj":"05:46","ai":"10.42","ak":"140","K":"07:29:37","P":"02:29:37","O":"01:24:09","M":"05:49","L":"10.34","N":"148","ab":"08:41:22","ag":"03:41:22","af":"01:11:45","ad":"06:29","ac":"9.26","ae":"180","i":"10:01:25","n":"05:01:25","m":"01:20:03","k":"06:31","j":"9.23","l":"193","S":"11:44:59","X":"06:44:59","W":"01:43:34","U":"07:02","T":"8.53","V":"206","u":"12:50:35","z":"07:50:35","y":"01:05:36","w":"07:10","v":"8.38","x":"206","c":"14:09:01","h":"09:09:01","g":"01:18:26","e":"07:43","d":"7.78","f":"227","E":"15:18:51","J":"10:18:51","I":"03:14","G":"05:24","F":"11.18","H":"242"}],"9999991678885B0001C47B0A":[{"a":"2025","B":"9999991678885B0001C47B0A","A":"HCH8NDMRA380C8","R":"Jakobsson, Viktor (SWE)","ap":"2016","C":"M35","ao":"UL90","D":"VarjeSteg","Y":"918","Z":"147","aa":"1233","b":"14:03:40","an":"6.52","ar":"I mål","aq":"05:00:00","Q":"2","o":"05:28:53","t":"00:28:53","s":"28:53","q":"08:46","p":"6.86","r":"463","ah":"06:24:57","am":"01:24:57","al":"56:04","aj":"07:26","ai":"8.08","ak":"589","K":"08:15:03","P":"03:15:03","O":"01:50:06","M":"07:36","L":"7.90","N":"687","ab":"09:49:27","ag":"04:49:27","af":"01:34:24","ad":"08:32","ac":"7.04","ae":"740","i":"11:35:23","n":"06:35:23","m":"01:45:56","k":"08:37","j":"6.97","l":"799","S":"14:00:21","X":"09:00:21","W":"02:24:58","U":"09:51","T":"6.10","V":"832","u":"15:30:33","z":"10:30:33","y":"01:30:12","w":"09:51","v":"6.09","x":"854","c":"17:18:01","h":"12:18:01","g":"01:47:28","e":"10:35","d":"5.68","f":"887","E":"19:03:40","J":"14:03:40","I":"05:38","G":"09:24","F":"6.39","H":"918"}],"HCH8NDMR1CA960A":[{"a":"2025","B":"HCH8NDMR1CA960A","A":"HCH8NDMRA400D7","R":"Mogren, Lars (SWE)","ap":"2413","C":"M55","ao":"UL90","D":"NORRKÖPING","Y":"512","Z":"26","aa":"657","b":"11:44:14","an":"7.81","ar":"I mål","aq":"05:00:00","o":"05:34:19","t":"00:34:19","s":"34:19","q":"10:24","p":"5.77","r":"856","ah":"06:43:58","am":"01:43:58","al":"01:09:39","aj":"09:14","ai":"6.50","ak":"973","K":"08:35:14","P":"03:35:14","O":"01:51:16","M":"07:41","L":"7.82","N":"936","ab":"09:57:36","ag":"04:57:36","af":"01:22:22","ad":"07:27","ac":"8.06","ae":"812","i":"11:24:34","n":"06:24:34","m":"01:26:58","k":"07:04","j":"8.49","l":"729","S":"13:20:04","X":"08:20:04","W":"01:55:30","U":"07:51","T":"7.65","V":"626","u":"14:27:44","z":"09:27:44","y":"01:07:40","w":"07:24","v":"8.12","x":"577","c":"15:40:22","h":"10:40:22","g":"01:12:38","e":"07:09","d":"8.40","f":"523","E":"16:44:14","J":"11:44:14","I":"03:00","G":"05:00","F":"11.97","H":"512"}],"HCH8NDMR1CAAC0A":[{"a":"2025","B":"HCH8NDMR1CAAC0A","A":"HCH8NDMRA43452","R":"Paralkar, Siddharth (USA)","ap":"2598","C":"M50","ao":"UL90","D":"Oakton","Y":"938","Z":"109","aa":"1263","b":"14:17:49","an":"6.41","ar":"I mål","aq":"05:00:00","o":"05:34:42","t":"00:34:42","s":"34:42","q":"10:31","p":"5.71","r":"887","ah":"06:38:59","am":"01:38:59","al":"01:04:17","aj":"08:31","ai":"7.05","ak":"878","K":"08:40:49","P":"03:40:49","O":"02:01:50","M":"08:25","L":"7.14","N":"995","ab":"10:20:42","ag":"05:20:42","af":"01:39:53","ad":"09:02","ac":"6.65","ae":"1011","i":"12:09:22","n":"07:09:22","m":"01:48:40","k":"08:50","j":"6.80","l":"1006","S":"14:30:22","X":"09:30:22","W":"02:21:00","U":"09:35","T":"6.27","V":"974","u":"15:58:00","z":"10:58:00","y":"01:27:38","w":"09:35","v":"6.27","x":"948","c":"17:41:27","h":"12:41:27","g":"01:43:27","e":"10:11","d":"5.90","f":"938","E":"19:17:49","J":"14:17:49","I":"04:18","G":"07:10","F":"8.40","H":"938"}],"HCH8NDMR1CB110A":[{"a":"2025","B":"HCH8NDMR1CB110A","A":"HCH8NDMRA512DD","R":"Skyrman, Carl (SWE)","ap":"3025","C":"M21","ao":"UL90","D":"SKÖVDE","Y":"951","Z":"306","aa":"1279","b":"14:23:49","an":"6.37","ar":"I mål","aq":"05:00:00","o":"05:34:47","t":"00:34:47","s":"34:47","q":"10:33","p":"5.69","r":"893","ah":"06:47:40","am":"01:47:40","al":"01:12:53","aj":"09:40","ai":"6.21","ak":"1044","K":"08:44:22","P":"03:44:22","O":"01:56:42","M":"08:03","L":"7.46","N":"1033","ab":"10:27:14","ag":"05:27:14","af":"01:42:52","ad":"09:18","ac":"6.46","ae":"1057","i":"12:12:21","n":"07:12:21","m":"01:45:07","k":"08:33","j":"7.03","l":"1020","S":"14:26:39","X":"09:26:39","W":"02:14:18","U":"09:08","T":"6.58","V":"965","u":"15:46:10","z":"10:46:10","y":"01:19:31","w":"08:41","v":"6.91","x":"916","c":"17:15:37","h":"12:15:37","g":"01:29:27","e":"08:48","d":"6.82","f":"881","E":"19:23:49","J":"14:23:49","I":"05:29","G":"09:09","F":"6.57","H":"951"}]}