{"9999991678885900000DF8AF":[{"a":"2014","B":"9999991678885900000DF8AF","A":"9999991678885900001BF0D5","R":"Drottenmyr, Jerker (SWE)","ap":"1285","C":"H40","ao":"UL-90","D":"Visborgs OK","Y":"469","Z":"128","aa":"523","b":"11:39:06","ar":"I mål","aq":"05:00:00","Q":"15","ah":"05:53:37","am":"00:53:37","al":"53:37","aj":"06:04","ai":"9.89","ak":"316","K":"07:24:00","P":"02:24:00","O":"01:30:23","M":"06:16","L":"9.60","N":"315","ab":"08:39:25","ag":"03:39:25","af":"01:15:25","ad":"07:03","ac":"8.51","ae":"360","i":"10:10:52","n":"05:10:52","m":"01:31:27","k":"07:30","j":"8.00","l":"391","S":"12:17:41","X":"07:17:41","W":"02:06:49","U":"08:42","T":"6.91","V":"416","u":"13:35:54","z":"08:35:54","y":"01:18:13","w":"08:42","v":"6.90","x":"424","c":"15:13:47","h":"10:13:47","g":"01:37:53","e":"09:54","d":"6.07","f":"449","E":"16:39:06","J":"11:39:06","I":"01:25:19","G":"08:17","F":"7.24","H":"469"},{"a":"2016","B":"9999991678885900000DF8AF","A":"9999991678885A000027045A","R":"Drottenmyr, Jerker (SWE)","ap":"1787","C":"M40","ao":"UL-90","D":"Visborgs OK","Y":"506","Z":"118","aa":"612","b":"12:18:37","ar":"I mål","aq":"05:00:00","Q":"15"},{"a":"2017","B":"9999991678885900000DF8AF","A":"9999991678885B00002AD4EB","R":"Drottenmyr, Jerker (SWE)","ap":"1779","C":"M40","ao":"UL-90","D":"Visborgs OK","Y":"582","Z":"128","aa":"725","b":"13:55:42","ar":"I mål","aq":"05:00:00","Q":"15","ah":"06:06:45","am":"01:06:45","al":"01:06:45","aj":"07:34","ai":"7.95","ak":"633","K":"07:47:34","P":"02:47:34","O":"01:40:49","M":"06:59","L":"8.61","N":"553","ab":"09:17:46","ag":"04:17:46","af":"01:30:12","ad":"08:26","ac":"7.12","ae":"533","i":"11:00:12","n":"06:00:12","m":"01:42:26","k":"08:24","j":"7.15","l":"553","S":"13:40:13","X":"08:40:13","W":"02:40:01","U":"10:58","T":"5.47","V":"582","u":"15:19:48","z":"10:19:48","y":"01:39:35","w":"11:04","v":"5.42","x":"587","c":"17:09:30","h":"12:09:30","g":"01:49:42","e":"11:05","d":"5.41","f":"583","E":"18:55:42","J":"13:55:42","I":"01:46:12","G":"10:19","F":"5.82","H":"582"},{"a":"2018","B":"9999991678885900000DF8AF","A":"9999991678885C00002BA7EB","R":"Drottenmyr, Jerker (SWE)","ap":"1477","C":"M45","ao":"UL-90","D":"Visborgs OK","Y":"639","Z":"124","aa":"811","b":"13:09:55","ar":"I mål","aq":"05:00:00","Q":"15","ah":"06:11:19","am":"01:11:19","al":"01:11:19","aj":"08:05","ai":"7.44","ak":"761","K":"07:55:08","P":"02:55:08","O":"01:43:49","M":"07:11","L":"8.36","N":"701","ab":"09:23:24","ag":"04:23:24","af":"01:28:16","ad":"08:15","ac":"7.27","ae":"661","i":"11:03:11","n":"06:03:11","m":"01:39:47","k":"08:11","j":"7.34","l":"657","S":"13:32:00","X":"08:32:00","W":"02:28:49","U":"10:12","T":"5.89","V":"670","u":"14:58:33","z":"09:58:33","y":"01:26:33","w":"09:37","v":"6.24","x":"650","c":"16:42:43","h":"11:42:43","g":"01:44:10","e":"10:32","d":"5.70","f":"649","E":"18:09:55","J":"13:09:55","I":"01:27:12","G":"08:28","F":"7.09","H":"639"},{"a":"2019","B":"9999991678885900000DF8AF","A":"999999167888680000410C46","R":"Drottenmyr, Jerker (SWE)","ap":"1492","C":"M45","ao":"UL-90","D":"Visborgs OK","Y":"643","Z":"130","aa":"829","b":"12:37:17","ar":"I mål","aq":"05:00:00","Q":"15","ah":"06:03:48","am":"01:03:48","al":"01:03:48","aj":"07:14","ai":"8.31","ak":"688","K":"07:44:10","P":"02:44:10","O":"01:40:22","M":"06:57","L":"8.64","N":"590","ab":"09:11:23","ag":"04:11:23","af":"01:27:13","ad":"08:10","ac":"7.36","ae":"609","i":"10:57:18","n":"05:57:18","m":"01:45:55","k":"08:41","j":"6.91","l":"666","S":"13:27:12","X":"08:27:12","W":"02:29:54","U":"10:17","T":"5.84","V":"702","u":"14:52:53","z":"09:52:53","y":"01:25:41","w":"09:32","v":"6.30","x":"687","c":"16:31:00","h":"11:31:00","g":"01:38:07","e":"09:55","d":"6.05","f":"676","E":"17:37:17","J":"12:37:17","I":"01:06:17","G":"06:27","F":"9.32","H":"643"},{"a":"2022","B":"9999991678885900000DF8AF","A":"HCH8NDMR9FE623","R":"Drottenmyr, Jerker (SWE)","ap":"1530","C":"M45","ao":"UL90","D":"Visborgs OK","Y":"736","Z":"146","aa":"1010","b":"14:39:42","ar":"I mål","aq":"05:00:00","Q":"15","ah":"06:13:10","am":"01:13:10","al":"01:13:10","aj":"08:17","ai":"7.25","ak":"818","K":"08:13:59","P":"03:13:59","O":"02:00:49","M":"08:22","L":"7.18","N":"802","ab":"09:55:22","ag":"04:55:22","af":"01:41:23","ad":"09:29","ac":"6.33","ae":"795","i":"11:55:59","n":"06:55:59","m":"02:00:37","k":"09:54","j":"6.07","l":"789","S":"14:43:44","X":"09:43:44","W":"02:47:45","U":"11:30","T":"5.22","V":"782","u":"16:19:23","z":"11:19:23","y":"01:35:39","w":"10:38","v":"5.65","x":"767","c":"18:09:44","h":"13:09:44","g":"01:50:21","e":"11:09","d":"5.38","f":"751","E":"19:39:42","J":"14:39:42","I":"01:29:58","G":"08:45","F":"6.87","H":"736"},{"a":"2023","B":"9999991678885900000DF8AF","A":"HCH8NDMRA0F663","R":"Drottenmyr, Jerker (SWE)","ap":"M1594","C":"M50","ao":"UL90","D":"Visborgs OK","Y":"701","Z":"81","aa":"966","b":"14:54:05","ar":"I mål","aq":"05:00:00","Q":"15","o":"05:34:28","t":"00:34:28","s":"34:28","q":"10:27","p":"5.75","r":"654","ah":"06:33:11","am":"01:33:11","al":"58:43","aj":"07:47","ai":"7.71","ak":"485","K":"08:34:05","P":"03:34:05","O":"02:00:54","M":"08:19","L":"7.22","N":"641","ab":"10:16:28","ag":"05:16:28","af":"01:42:23","ad":"09:16","ac":"6.48","ae":"682","i":"12:16:16","n":"07:16:16","m":"01:59:48","k":"09:41","j":"6.20","l":"716","S":"15:00:28","X":"10:00:28","W":"02:44:12","U":"11:03","T":"5.44","V":"734","u":"16:36:03","z":"11:36:03","y":"01:35:35","w":"10:24","v":"5.77","x":"726","c":"18:21:52","h":"13:21:52","g":"01:45:49","e":"10:26","d":"5.75","f":"711","E":"19:54:05","J":"14:54:05","I":"01:32:13","G":"10:10","F":"5.91","H":"701"},{"a":"2024","B":"9999991678885900000DF8AF","A":"HCH8NDMRA1A117","R":"Drottenmyr, Jerker (SWE)","ap":"2300","C":"M50","ao":"UL90","D":"Visborgs OK","Y":"826","Z":"85","aa":"1155","b":"14:50:57","ar":"I mål","aq":"05:00:00","Q":"15","o":"05:35:55","t":"00:35:55","s":"35:55","q":"10:54","p":"5.51","r":"774","ah":"06:44:44","am":"01:44:44","al":"01:08:49","aj":"09:07","ai":"6.58","ak":"919","K":"08:54:42","P":"03:54:42","O":"02:09:58","M":"08:56","L":"6.72","N":"953","ab":"10:35:02","ag":"05:35:02","af":"01:40:20","ad":"09:05","ac":"6.61","ae":"909","i":"12:29:15","n":"07:29:15","m":"01:54:13","k":"09:15","j":"6.49","l":"895","S":"14:59:29","X":"09:59:29","W":"02:30:14","U":"10:13","T":"5.88","V":"869","u":"16:35:36","z":"11:35:36","y":"01:36:07","w":"10:29","v":"5.73","x":"857","c":"18:23:22","h":"13:23:22","g":"01:47:46","e":"10:38","d":"5.65","f":"849","E":"19:50:57","J":"14:50:57","I":"01:27:35","G":"09:52","F":"6.09","H":"826"},{"a":"2025","B":"9999991678885900000DF8AF","A":"HCH8NDMRA58193","R":"Drottenmyr, Jerker (SWE)","ap":"3041","C":"M50","ao":"UL90","D":"Skogsluffarnas OK","Y":"1079","Z":"128","aa":"1521","b":"16:11:52","an":"5.66","ar":"I mål","aq":"05:00:00","Q":"15","o":"05:31:39","t":"00:31:39","s":"31:39","q":"09:36","p":"6.26","r":"609","ah":"06:30:52","am":"01:30:52","al":"59:13","aj":"07:51","ai":"7.65","ak":"727","K":"08:40:14","P":"03:40:14","O":"02:09:22","M":"08:56","L":"6.73","N":"989","ab":"10:34:10","ag":"05:34:10","af":"01:53:56","ad":"10:18","ac":"5.83","ae":"1090","i":"12:36:11","n":"07:36:11","m":"02:02:01","k":"09:55","j":"6.05","l":"1102","S":"15:30:08","X":"10:30:08","W":"02:53:57","U":"11:49","T":"5.08","V":"1102","u":"17:01:13","z":"12:01:13","y":"01:31:05","w":"09:57","v":"6.03","x":"1072","c":"18:50:01","h":"13:50:01","g":"01:48:48","e":"10:42","d":"5.61","f":"1067","E":"21:11:52","J":"16:11:52","I":"06:30","G":"10:50","F":"5.54","H":"1079"}],"9999991678885900001153AF":[{"a":"2014","B":"9999991678885900001153AF","A":"9999991678885900001BFB3C","R":"Smith, Edvard (SWE)","ap":"1542","C":"H40","ao":"UL-90","D":"Karlstad","Y":"152","Z":"40","aa":"162","b":"09:16:49","ar":"I mål","aq":"05:00:00","Q":"8","ah":"05:49:38","am":"00:49:38","al":"49:38","aj":"05:37","ai":"10.69","ak":"151","K":"07:09:08","P":"02:09:08","O":"01:19:30","M":"05:30","L":"10.91","N":"126","ab":"08:09:55","ag":"03:09:55","af":"01:00:47","ad":"05:41","ac":"10.56","ae":"126","i":"09:25:10","n":"04:25:10","m":"01:15:15","k":"06:11","j":"9.73","l":"138","S":"11:06:53","X":"06:06:53","W":"01:41:43","U":"06:59","T":"8.61","V":"138","u":"12:13:14","z":"07:13:14","y":"01:06:21","w":"07:23","v":"8.14","x":"156","c":"13:21:05","h":"08:21:05","g":"01:07:51","e":"06:52","d":"8.75","f":"159","E":"14:16:49","J":"09:16:49","I":"55:44","G":"05:25","F":"11.09","H":"152"}],"9999991678885A0000137FAF":[{"a":"2015","B":"9999991678885A0000137FAF","A":"9999991678885A00001FA59B","R":"Löfstrand, Andreas (SWE)","ap":"1640","C":"M21","ao":"UL-90","D":"Kungsängen","Y":"362","Z":"90","aa":"403","b":"10:24:05","ar":"I mål","aq":"05:00:00","ah":"05:55:30","am":"00:55:30","al":"55:30","aj":"06:17","ai":"9.56","ak":"438","K":"07:31:12","P":"02:31:12","O":"01:35:42","M":"06:38","L":"9.07","N":"453","ab":"08:41:04","ag":"03:41:04","af":"01:09:52","ad":"06:32","ac":"9.19","ae":"453","i":"10:01:56","n":"05:01:56","m":"01:20:52","k":"06:38","j":"9.05","l":"418","S":"11:51:06","X":"06:51:06","W":"01:49:10","U":"07:29","T":"8.02","V":"391","u":"13:05:53","z":"08:05:53","y":"01:14:47","w":"08:19","v":"7.22","x":"397","c":"14:20:09","h":"09:20:09","g":"01:14:16","e":"07:31","d":"8.00","f":"375","E":"15:24:05","J":"10:24:05","I":"01:03:56","G":"06:13","F":"9.67","H":"362"}],"HCH8NDMR1CAFFAF":[{"a":"2016","B":"HCH8NDMR1CAFFAF","A":"9999991678885A0000224C42","R":"Wallander, Jonas (SWE)","ap":"1286","C":"M45","ao":"UL-90","D":"Ununge IF","ar":"Startade inte","aq":"05:00:00","Q":"9"},{"a":"2017","B":"HCH8NDMR1CAFFAF","A":"9999991678885A0000277AA0","R":"Wallander, Jonas (SWE)","ap":"1255","C":"M45","ao":"UL-90","D":"VÄDDÖ","Y":"219","Z":"43","aa":"253","b":"10:06:46","ar":"I mål","aq":"05:00:00","Q":"9","ah":"05:51:13","am":"00:51:13","al":"51:13","aj":"05:48","ai":"10.36","ak":"193","K":"07:16:36","P":"02:16:36","O":"01:25:23","M":"05:55","L":"10.16","N":"196","ab":"08:30:45","ag":"03:30:45","af":"01:14:09","ad":"06:56","ac":"8.66","ae":"226","i":"09:53:43","n":"04:53:43","m":"01:22:58","k":"06:49","j":"8.82","l":"238","S":"11:42:58","X":"06:42:58","W":"01:49:15","U":"07:29","T":"8.02","V":"236","u":"12:50:16","z":"07:50:16","y":"01:07:18","w":"07:29","v":"8.02","x":"228","c":"14:03:32","h":"09:03:32","g":"01:13:16","e":"07:25","d":"8.11","f":"222","E":"15:06:46","J":"10:06:46","I":"01:03:14","G":"06:09","F":"9.77","H":"219"},{"a":"2024","B":"HCH8NDMR1CAFFAF","A":"HCH8NDMRA196FA","R":"Wallander, Jonas (SWE)","ap":"2150","C":"M55","ao":"UL90","D":"Häverödal sk","Y":"587","Z":"28","aa":"747","b":"12:50:09","ar":"I mål","aq":"05:00:00","Q":"9","o":"05:36:45","t":"00:36:45","s":"36:45","q":"11:09","p":"5.39","r":"836","ah":"06:36:03","am":"01:36:03","al":"59:18","aj":"07:52","ai":"7.64","ak":"731","K":"08:30:00","P":"03:30:00","O":"01:53:57","M":"07:50","L":"7.66","N":"722","ab":"09:58:41","ag":"04:58:41","af":"01:28:41","ad":"08:02","ac":"7.48","ae":"676","i":"11:36:18","n":"06:36:18","m":"01:37:37","k":"07:55","j":"7.59","l":"651","S":"13:48:09","X":"08:48:09","W":"02:11:51","U":"08:58","T":"6.70","V":"641","u":"15:10:18","z":"10:10:18","y":"01:22:09","w":"08:58","v":"6.70","x":"626","c":"16:41:29","h":"11:41:29","g":"01:31:11","e":"09:00","d":"6.68","f":"617","E":"17:50:09","J":"12:50:09","I":"01:08:40","G":"07:44","F":"7.77","H":"587"},{"a":"2025","B":"HCH8NDMR1CAFFAF","A":"HCH8NDMRA3EF69","R":"Wallander, Jonas (SWE)","ap":"2243","C":"M55","ao":"UL90","D":"Häverödals sk","Y":"792","Z":"47","aa":"1045","b":"13:16:43","an":"6.90","ar":"I mål","aq":"05:00:00","Q":"9","o":"05:35:22","t":"00:35:22","s":"35:22","q":"10:44","p":"5.60","r":"938","ah":"06:39:34","am":"01:39:34","al":"01:04:12","aj":"08:31","ai":"7.06","ak":"902","K":"08:30:38","P":"03:30:38","O":"01:51:04","M":"07:40","L":"7.83","N":"859","ab":"10:09:10","ag":"05:09:10","af":"01:38:32","ad":"08:55","ac":"6.74","ae":"905","i":"11:58:03","n":"06:58:03","m":"01:48:53","k":"08:51","j":"6.78","l":"935","S":"14:17:17","X":"09:17:17","W":"02:19:14","U":"09:28","T":"6.35","V":"921","u":"15:37:35","z":"10:37:35","y":"01:20:18","w":"08:46","v":"6.85","x":"886","c":"17:05:22","h":"12:05:22","g":"01:27:47","e":"08:38","d":"6.95","f":"835","E":"18:16:43","J":"13:16:43","I":"03:36","G":"06:00","F":"10.03","H":"792"}],"9999991678885900000C9CAF":[{"a":"2016","B":"9999991678885900000C9CAF","A":"9999991678885A000026E087","R":"Belfrage, Anna (SWE)","ap":"3181","C":"W21","ao":"UL-90","D":"Stavanger","Y":"132","Z":"42","aa":"707","b":"13:52:47","ar":"I mål","aq":"05:00:00","Q":"1"},{"a":"2017","B":"9999991678885900000C9CAF","A":"9999991678885B0000295FEC","R":"Belfrage, Anna (SWE)","ap":"3118","C":"W35","ao":"UL-90","D":"Feministiskt initiativ","Y":"99","Z":"22","aa":"559","b":"11:59:46","ar":"I mål","aq":"05:00:00","Q":"1","ah":"06:00:35","am":"01:00:35","al":"01:00:35","aj":"06:52","ai":"8.76","ak":"101","K":"07:38:12","P":"02:38:12","O":"01:37:37","M":"06:46","L":"8.89","N":"86","ab":"09:03:39","ag":"04:03:39","af":"01:25:27","ad":"08:00","ac":"7.51","ae":"79","i":"10:43:18","n":"05:43:18","m":"01:39:39","k":"08:11","j":"7.35","l":"88","S":"12:54:31","X":"07:54:31","W":"02:11:13","U":"09:00","T":"6.68","V":"96","u":"14:18:50","z":"09:18:50","y":"01:24:19","w":"09:23","v":"6.40","x":"99","c":"15:46:13","h":"10:46:13","g":"01:27:23","e":"08:50","d":"6.80","f":"99","E":"16:59:46","J":"11:59:46","I":"01:13:33","G":"07:09","F":"8.40","H":"99"},{"a":"2018","B":"9999991678885900000C9CAF","A":"9999991678885F00003186DC","R":"Belfrage, Anna (SWE)","ap":"3282","C":"W35","ao":"UL-90","D":"Feministiskt initiativ","Y":"135","Z":"21","aa":"667","b":"12:01:09","ar":"I mål","aq":"05:00:00","Q":"1","ah":"06:00:42","am":"01:00:42","al":"01:00:42","aj":"06:52","ai":"8.74","ak":"118","K":"07:35:17","P":"02:35:17","O":"01:34:35","M":"06:33","L":"9.17","N":"103","ab":"08:57:41","ag":"03:57:41","af":"01:22:24","ad":"07:43","ac":"7.79","ae":"103","i":"10:39:58","n":"05:39:58","m":"01:42:17","k":"08:24","j":"7.16","l":"125","S":"12:44:05","X":"07:44:05","W":"02:04:07","U":"08:31","T":"7.06","V":"119","u":"14:12:05","z":"09:12:05","y":"01:28:00","w":"09:47","v":"6.14","x":"128","c":"15:44:39","h":"10:44:39","g":"01:32:34","e":"09:22","d":"6.42","f":"131","E":"17:01:09","J":"12:01:09","I":"01:16:30","G":"07:26","F":"8.08","H":"135"}],"9999991678885A000014CFAF":[{"a":"2016","B":"9999991678885A000014CFAF","A":"9999991678885A0000221796","R":"Kaiser, Andreas (SWE)","ap":"1058","C":"M40","ao":"UL-90","D":"Svenska Ducatiklubben","ar":"Startade inte","aq":"05:00:00"},{"a":"2022","B":"9999991678885A000014CFAF","A":"9999991678887600009AAD4F","R":"Kaiser, Andreas (SWE)","ap":"1359","C":"M50","ao":"UL90","D":"Svenska Ducatiklubben","Y":"199","Z":"18","aa":"245","b":"10:09:08","ar":"I mål","aq":"05:00:00","ah":"05:53:31","am":"00:53:31","al":"53:31","aj":"06:04","ai":"9.91","ak":"240","K":"07:27:15","P":"02:27:15","O":"01:33:44","M":"06:29","L":"9.26","N":"273","ab":"08:44:38","ag":"03:44:38","af":"01:17:23","ad":"07:14","ac":"8.30","ae":"273","i":"10:20:12","n":"05:20:12","m":"01:35:34","k":"07:50","j":"7.66","l":"327","S":"12:03:59","X":"07:03:59","W":"01:43:47","U":"07:07","T":"8.44","V":"263","u":"13:05:55","z":"08:05:55","y":"01:01:56","w":"06:53","v":"8.72","x":"239","c":"14:11:53","h":"09:11:53","g":"01:05:58","e":"06:40","d":"9.00","f":"212","E":"15:09:08","J":"10:09:08","I":"57:15","G":"05:34","F":"10.80","H":"199"}],"9999991678885A000013C5AF":[{"a":"2016","B":"9999991678885A000013C5AF","A":"9999991678885A0000259E26","R":"Roos, Johan (SWE)","ap":"1544","C":"M35","ao":"UL-90","D":"Bromma","Y":"104","Z":"19","aa":"118","b":"08:52:55","ar":"I mål","aq":"05:00:00"}],"9999991678885B0001C383AF":[{"a":"2017","B":"9999991678885B0001C383AF","A":"9999991678885B00002AB8F7","R":"Kroon, Tommy (SWE)","ap":"1719","C":"M35","ao":"UL-90","D":"Sturefors","Y":"356","Z":"82","aa":"421","b":"11:04:23","ar":"I mål","aq":"05:00:00","ah":"05:57:19","am":"00:57:19","al":"57:19","aj":"06:30","ai":"9.26","ak":"391","K":"07:28:01","P":"02:28:01","O":"01:30:42","M":"06:17","L":"9.57","N":"333","ab":"08:39:59","ag":"03:39:59","af":"01:11:58","ad":"06:44","ac":"8.92","ae":"286","i":"10:02:03","n":"05:02:03","m":"01:22:04","k":"06:44","j":"8.92","l":"276","S":"12:14:27","X":"07:14:27","W":"02:12:24","U":"09:05","T":"6.62","V":"340","u":"13:26:55","z":"08:26:55","y":"01:12:28","w":"08:04","v":"7.45","x":"339","c":"14:52:13","h":"09:52:13","g":"01:25:18","e":"08:37","d":"6.96","f":"356","E":"16:04:23","J":"11:04:23","I":"01:12:10","G":"07:01","F":"8.56","H":"356"}],"9999991678885A0001C266AF":[{"a":"2017","B":"9999991678885A0001C266AF","A":"9999991678885A000027A940","R":"Lernell, Johan (SWE)","ap":"1279","C":"M40","ao":"UL-90","D":"Enskede","ar":"Startade inte","aq":"05:00:00"}],"9999991678885B0001C434AF":[{"a":"2017","B":"9999991678885B0001C434AF","A":"9999991678885B00002AA66E","R":"Lundberg, Malin (SWE)","ap":"3170","C":"W40","ao":"UL-90","D":"Graninge Alliansen","Y":"74","Z":"24","aa":"459","b":"11:23:17","ar":"I mål","aq":"05:00:00","Q":"3","ah":"05:55:04","am":"00:55:04","al":"55:04","aj":"06:14","ai":"9.63","ak":"54","K":"07:24:27","P":"02:24:27","O":"01:29:23","M":"06:11","L":"9.71","N":"42","ab":"08:46:37","ag":"03:46:37","af":"01:22:10","ad":"07:41","ac":"7.81","ae":"49","i":"10:11:30","n":"05:11:30","m":"01:24:53","k":"06:58","j":"8.62","l":"49","S":"12:23:46","X":"07:23:46","W":"02:12:16","U":"09:04","T":"6.62","V":"68","u":"13:36:27","z":"08:36:27","y":"01:12:41","w":"08:05","v":"7.43","x":"65","c":"15:09:03","h":"10:09:03","g":"01:32:36","e":"09:22","d":"6.41","f":"75","E":"16:23:17","J":"11:23:17","I":"01:14:14","G":"07:13","F":"8.33","H":"74"},{"a":"2018","B":"9999991678885B0001C434AF","A":"9999991678885B00002C4594","R":"Lundberg, Malin (SWE)","ap":"3224","C":"W40","ao":"UL-90","D":"Graninge Alliansen","Y":"129","Z":"31","aa":"651","b":"11:53:19","ar":"I mål","aq":"05:00:00","Q":"3","ah":"05:58:01","am":"00:58:01","al":"58:01","aj":"06:34","ai":"9.14","ak":"85","K":"07:34:30","P":"02:34:30","O":"01:36:29","M":"06:41","L":"8.99","N":"101","ab":"08:52:52","ag":"03:52:52","af":"01:18:22","ad":"07:20","ac":"8.19","ae":"86","i":"10:19:42","n":"05:19:42","m":"01:26:50","k":"07:08","j":"8.43","l":"84","S":"12:19:11","X":"07:19:11","W":"01:59:29","U":"08:12","T":"7.33","V":"84","u":"13:45:31","z":"08:45:31","y":"01:26:20","w":"09:36","v":"6.26","x":"107","c":"15:26:38","h":"10:26:38","g":"01:41:07","e":"10:13","d":"5.87","f":"117","E":"16:53:19","J":"11:53:19","I":"01:26:41","G":"08:25","F":"7.13","H":"129"},{"a":"2023","B":"9999991678885B0001C434AF","A":"HCH8NDMRA0F694","R":"Lundberg, Malin (SWE)","ap":"W1244","C":"W45","ao":"UL90","D":"Graninge Alliansen","ar":"Startade inte","aq":"05:00:00","Q":"3"}],"9999991678885900001042AF":[{"a":"2018","B":"9999991678885900001042AF","A":"9999991678885B00002B0600","R":"Karlsson, Mats (SWE)","ap":"1133","C":"M50","ao":"UL-90","D":"IFK Skövde FIK","ar":"Brutit","aq":"05:00:00","Q":"4","ah":"06:03:59","am":"01:03:59","al":"01:03:59","aj":"07:15","ai":"8.29","ak":"605","K":"07:44:14","P":"02:44:14","O":"01:40:15","M":"06:56","L":"8.66","N":"573","ab":"09:06:39","ag":"04:06:39","af":"01:22:25","ad":"07:43","ac":"7.79","ae":"550","i":"10:55:18","n":"05:55:18","m":"01:48:39","k":"08:55","j":"6.74","l":"621","S":"12:51:10","X":"07:51:10","W":"01:55:52","U":"07:57","T":"7.56","V":"534","u":"14:28:53","z":"09:28:53","y":"01:37:43","w":"10:52","v":"5.53","x":"579"},{"a":"2019","B":"9999991678885900001042AF","A":"9999991678886300003CA8F8","R":"Karlsson, Mats (SWE)","ap":"1418","C":"M50","ao":"UL-90","D":"IFK Skövde FIK","Y":"716","Z":"89","aa":"949","b":"13:24:03","ar":"I mål","aq":"05:00:00","Q":"4","ah":"06:11:20","am":"01:11:20","al":"01:11:20","aj":"08:05","ai":"7.44","ak":"876","K":"08:19:24","P":"03:19:24","O":"02:08:04","M":"08:52","L":"6.77","N":"884","ab":"09:51:53","ag":"04:51:53","af":"01:32:29","ad":"08:39","ac":"6.94","ae":"856","i":"11:50:33","n":"06:50:33","m":"01:58:40","k":"09:44","j":"6.17","l":"855","S":"14:09:33","X":"09:09:33","W":"02:19:00","U":"09:32","T":"6.30","V":"810","u":"15:33:25","z":"10:33:25","y":"01:23:52","w":"09:20","v":"6.44","x":"773","c":"17:10:10","h":"12:10:10","g":"01:36:45","e":"09:47","d":"6.14","f":"746","E":"18:24:03","J":"13:24:03","I":"01:13:53","G":"07:11","F":"8.36","H":"716"},{"a":"2022","B":"9999991678885900001042AF","A":"99999916788876000089092A","R":"Karlsson, Mats (SWE)","ap":"1219","C":"M50","ao":"UL90","D":"IFK Skövde FIK","ar":"Brutit","aq":"05:00:00","Q":"4","ah":"06:04:35","am":"01:04:35","al":"01:04:35","aj":"07:19","ai":"8.21","ak":"568","K":"07:56:30","P":"02:56:30","O":"01:51:55","M":"07:45","L":"7.75","N":"591","ab":"09:35:12","ag":"04:35:12","af":"01:38:42","ad":"09:14","ac":"6.50","ae":"650","i":"12:12:09","n":"07:12:09","m":"02:36:57","k":"12:52","j":"4.66","l":"821"}],"9999991678885900001025AF":[{"a":"2018","B":"9999991678885900001025AF","A":"9999991678885B00002B7B1D","R":"Njaastad, Terje (NOR)","ap":"1435","C":"M45","ao":"UL-90","D":"Team Nettbuss","Y":"357","Z":"71","aa":"432","b":"10:44:47","ar":"I mål","aq":"05:00:00","Q":"9","ah":"06:03:25","am":"01:03:25","al":"01:03:25","aj":"07:11","ai":"8.36","ak":"592","K":"07:39:07","P":"02:39:07","O":"01:35:42","M":"06:38","L":"9.07","N":"518","ab":"08:58:43","ag":"03:58:43","af":"01:19:36","ad":"07:27","ac":"8.07","ae":"494","i":"10:23:54","n":"05:23:54","m":"01:25:11","k":"06:59","j":"8.59","l":"451","S":"12:13:49","X":"07:13:49","W":"01:49:55","U":"07:32","T":"7.97","V":"390","u":"13:21:05","z":"08:21:05","y":"01:07:16","w":"07:29","v":"8.03","x":"369","c":"14:39:37","h":"09:39:37","g":"01:18:32","e":"07:56","d":"7.56","f":"357","E":"15:44:47","J":"10:44:47","I":"01:05:10","G":"06:20","F":"9.48","H":"357"},{"a":"2022","B":"9999991678885900001025AF","A":"HCH8NDMR9C5984","R":"Njaastad, Terje (NOR)","ap":"1533","C":"M50","ao":"UL90","D":"Drammen","ar":"Startade inte","aq":"05:00:00","Q":"9"}],"9999991678885A000014AFAF":[{"a":"2019","B":"9999991678885A000014AFAF","A":"99999916788862000035EF17","R":"Broström, Peter (SWE)","ap":"1310","C":"M55","ao":"UL-90","D":"Kalmar","ar":"Startade inte","aq":"05:00:00"}],"9999991678885A000013D0AF":[{"a":"2019","B":"9999991678885A000013D0AF","A":"999999167888690000483E21","R":"Gustafsson, Åsa (SWE)","ap":"3255","C":"W21","ao":"UL-90","D":"Johanneshov","Y":"50","Z":"16","aa":"335","b":"10:12:38","ar":"I mål","aq":"05:00:00","Q":"1","ah":"05:48:28","am":"00:48:28","al":"48:28","aj":"05:29","ai":"10.95","ak":"23","K":"07:13:28","P":"02:13:28","O":"01:25:00","M":"05:53","L":"10.21","N":"27","ab":"08:29:56","ag":"03:29:56","af":"01:16:28","ad":"07:09","ac":"8.40","ae":"38","i":"09:55:16","n":"04:55:16","m":"01:25:20","k":"07:00","j":"8.58","l":"42","S":"11:43:56","X":"06:43:56","W":"01:48:40","U":"07:27","T":"8.06","V":"43","u":"12:48:44","z":"07:48:44","y":"01:04:48","w":"07:12","v":"8.33","x":"43","c":"14:06:53","h":"09:06:53","g":"01:18:09","e":"07:54","d":"7.60","f":"46","E":"15:12:38","J":"10:12:38","I":"01:05:45","G":"06:24","F":"9.40","H":"50"}],"9999991678885900000BE4AF":[{"a":"2022","B":"9999991678885900000BE4AF","A":"HCH8NDMR9FA944","R":"Haglund, Anders (SWE)","ap":"2166","C":"M45","ao":"UL90","D":"OK Milan","Y":"270","Z":"57","aa":"346","b":"10:45:53","ar":"I mål","aq":"05:00:00","Q":"7","ah":"05:57:29","am":"00:57:29","al":"57:29","aj":"06:31","ai":"9.23","ak":"339","K":"07:32:47","P":"02:32:47","O":"01:35:18","M":"06:36","L":"9.10","N":"325","ab":"08:49:13","ag":"03:49:13","af":"01:16:26","ad":"07:09","ac":"8.40","ae":"309","i":"10:14:33","n":"05:14:33","m":"01:25:20","k":"07:00","j":"8.58","l":"295","S":"12:06:03","X":"07:06:03","W":"01:51:30","U":"07:39","T":"7.86","V":"273","u":"13:20:07","z":"08:20:07","y":"01:14:04","w":"08:14","v":"7.29","x":"274","c":"14:41:22","h":"09:41:22","g":"01:21:15","e":"08:13","d":"7.31","f":"275","E":"15:45:53","J":"10:45:53","I":"01:04:31","G":"06:16","F":"9.58","H":"270"}],"BH28NDMR1C966AF":[{"a":"2023","B":"BH28NDMR1C966AF","A":"BH28NDMRA09DF4","R":"Rajab, Usman (SWE)","ap":"M1442","C":"M35","ao":"UL90","D":"Stockholm","Y":"695","Z":"105","aa":"950","b":"14:50:18","ar":"I mål","aq":"05:00:00","o":"05:35:26","t":"00:35:26","s":"35:26","q":"10:45","p":"5.59","r":"719","ah":"06:44:01","am":"01:44:01","al":"01:08:35","aj":"09:06","ai":"6.61","ak":"701","K":"08:38:28","P":"03:38:28","O":"01:54:27","M":"07:52","L":"7.63","N":"687","ab":"10:21:32","ag":"05:21:32","af":"01:43:04","ad":"09:20","ac":"6.43","ae":"705","i":"12:20:50","n":"07:20:50","m":"01:59:18","k":"09:39","j":"6.22","l":"734","S":"14:52:14","X":"09:52:14","W":"02:31:24","U":"10:11","T":"5.89","V":"721","u":"16:30:33","z":"11:30:33","y":"01:38:19","w":"10:42","v":"5.61","x":"716","c":"18:19:37","h":"13:19:37","g":"01:49:04","e":"10:45","d":"5.58","f":"707","E":"19:50:18","J":"14:50:18","I":"01:30:41","G":"10:00","F":"6.01","H":"695"}],"HCH8NDMR1C9D0AF":[{"a":"2024","B":"HCH8NDMR1C9D0AF","A":"HCH8NDMRA1BF6B","R":"Enger, Ida (SWE)","ap":"1183","C":"W50","ao":"UL90","D":"Pålsboda goif","Y":"117","Z":"8","aa":"587","b":"12:03:49","ar":"I mål","aq":"05:00:00","o":"05:33:39","t":"00:33:39","s":"33:39","q":"10:12","p":"5.88","r":"226","ah":"06:27:36","am":"01:27:36","al":"53:57","aj":"07:09","ai":"8.40","ak":"147","K":"08:10:56","P":"03:10:56","O":"01:43:20","M":"07:07","L":"8.45","N":"124","ab":"09:38:57","ag":"04:38:57","af":"01:28:01","ad":"07:58","ac":"7.53","ae":"120","i":"11:10:19","n":"06:10:19","m":"01:31:22","k":"07:24","j":"8.11","l":"117","S":"13:19:28","X":"08:19:28","W":"02:09:09","U":"08:47","T":"6.84","V":"122","u":"14:37:45","z":"09:37:45","y":"01:18:17","w":"08:32","v":"7.03","x":"125","c":"15:57:11","h":"10:57:11","g":"01:19:26","e":"07:50","d":"7.67","f":"120","E":"17:03:49","J":"12:03:49","I":"01:06:38","G":"07:30","F":"8.00","H":"117"}],"HCH8NDMR1CA6BAF":[{"a":"2024","B":"HCH8NDMR1CA6BAF","A":"HCH8NDMRA327AB","R":"Hansson, Agnes (SWE)","ap":"1406","C":"W21","ao":"UL90","D":"SEB","Y":"169","Z":"45","aa":"778","b":"12:56:40","ar":"I mål","aq":"05:00:00","o":"05:35:58","t":"00:35:58","s":"35:58","q":"10:54","p":"5.51","r":"295","ah":"06:36:37","am":"01:36:37","al":"01:00:39","aj":"08:02","ai":"7.47","ak":"269","K":"08:30:01","P":"03:30:01","O":"01:53:24","M":"07:48","L":"7.70","N":"221","ab":"10:06:19","ag":"05:06:19","af":"01:36:18","ad":"08:43","ac":"6.88","ae":"214","i":"11:54:45","n":"06:54:45","m":"01:48:26","k":"08:47","j":"6.83","l":"231","S":"14:01:01","X":"09:01:01","W":"02:06:16","U":"08:35","T":"7.00","V":"207","u":"15:20:15","z":"10:20:15","y":"01:19:14","w":"08:39","v":"6.95","x":"181","c":"16:49:54","h":"11:49:54","g":"01:29:39","e":"08:50","d":"6.79","f":"183","E":"17:56:40","J":"12:56:40","I":"01:06:46","G":"07:31","F":"7.99","H":"169"},{"a":"2025","B":"HCH8NDMR1CA6BAF","A":"HCH8NDMRA574C8","R":"Hansson, Agnes (SWE)","ap":"1516","C":"W21","ao":"UL90","D":"STOCKHOLM","Y":"217","Z":"62","aa":"910","b":"12:44:51","an":"7.19","ar":"I mål","aq":"05:00:00","o":"05:32:39","t":"00:32:39","s":"32:39","q":"09:54","p":"6.07","r":"228","ah":"06:28:13","am":"01:28:13","al":"55:34","aj":"07:22","ai":"8.15","ak":"199","K":"08:16:45","P":"03:16:45","O":"01:48:32","M":"07:30","L":"8.02","N":"211","ab":"09:52:04","ag":"04:52:04","af":"01:35:19","ad":"08:37","ac":"6.97","ae":"226","i":"11:38:24","n":"06:38:24","m":"01:46:20","k":"08:39","j":"6.95","l":"237","S":"13:51:00","X":"08:51:00","W":"02:12:36","U":"09:01","T":"6.67","V":"240","u":"15:14:05","z":"10:14:05","y":"01:23:05","w":"09:05","v":"6.62","x":"234","c":"16:40:16","h":"11:40:16","g":"01:26:11","e":"08:29","d":"7.08","f":"231","E":"17:44:51","J":"12:44:51","I":"02:26","G":"04:04","F":"14.76","H":"217"}],"HCH8NDMR1CAC0AF":[{"a":"2025","B":"HCH8NDMR1CAC0AF","A":"HCH8NDMRA48D16","R":"Betsén, Petter (SWE)","ap":"2758","C":"M21","ao":"UL90","D":"ISBHIK","Y":"412","Z":"120","aa":"520","b":"11:16:41","an":"8.13","ar":"I mål","aq":"05:00:00","o":"05:30:56","t":"00:30:56","s":"30:56","q":"09:23","p":"6.40","r":"578","ah":"06:23:05","am":"01:23:05","al":"52:09","aj":"06:55","ai":"8.69","ak":"548","K":"08:00:32","P":"03:00:32","O":"01:37:27","M":"06:44","L":"8.93","N":"511","ab":"09:14:27","ag":"04:14:27","af":"01:13:55","ad":"06:41","ac":"8.99","ae":"453","i":"10:37:47","n":"05:37:47","m":"01:23:20","k":"06:47","j":"8.86","l":"412","S":"12:33:30","X":"07:33:30","W":"01:55:43","U":"07:52","T":"7.64","V":"411","u":"13:47:48","z":"08:47:48","y":"01:14:18","w":"08:07","v":"7.40","x":"410","c":"15:06:34","h":"10:06:34","g":"01:18:46","e":"07:45","d":"7.75","f":"402","E":"16:16:41","J":"11:16:41","I":"03:17","G":"05:29","F":"10.96","H":"412"}],"HCH8NDMR1CA90AF":[{"a":"2025","B":"HCH8NDMR1CA90AF","A":"HCH8NDMRA3EFB2","R":"Bjernulf, Simon (SWE)","ap":"2247","C":"M21","ao":"UL90","D":"Koppjärk","Y":"588","Z":"172","aa":"758","b":"12:06:50","an":"7.57","ar":"I mål","aq":"05:00:00","Q":"1","o":"05:33:27","t":"00:33:27","s":"33:27","q":"10:09","p":"5.92","r":"778","ah":"06:28:36","am":"01:28:36","al":"55:09","aj":"07:19","ai":"8.21","ak":"683","K":"08:08:56","P":"03:08:56","O":"01:40:20","M":"06:56","L":"8.67","N":"615","ab":"09:24:50","ag":"04:24:50","af":"01:15:54","ad":"06:52","ac":"8.75","ae":"540","i":"10:54:07","n":"05:54:07","m":"01:29:17","k":"07:16","j":"8.27","l":"509","S":"13:01:02","X":"08:01:02","W":"02:06:55","U":"08:37","T":"6.96","V":"540","u":"14:25:38","z":"09:25:38","y":"01:24:36","w":"09:15","v":"6.50","x":"571","c":"15:53:29","h":"10:53:29","g":"01:27:51","e":"08:39","d":"6.95","f":"582","E":"17:06:50","J":"12:06:50","I":"03:22","G":"05:37","F":"10.69","H":"588"}],"HCH8NDMR1CA92AF":[{"a":"2025","B":"HCH8NDMR1CA92AF","A":"HCH8NDMRA3F917","R":"Koppelo, Anton (SWE)","ap":"2368","C":"M21","ao":"UL90","D":"VÄRNAMO","Y":"1012","Z":"327","aa":"1385","b":"14:58:01","an":"6.12","ar":"I mål","aq":"05:00:00","o":"05:31:53","t":"00:31:53","s":"31:53","q":"09:40","p":"6.21","r":"624","ah":"06:39:07","am":"01:39:07","al":"01:07:14","aj":"08:55","ai":"6.74","ak":"887","K":"08:43:29","P":"03:43:29","O":"02:04:22","M":"08:35","L":"7.00","N":"1031","ab":"10:22:18","ag":"05:22:18","af":"01:38:49","ad":"08:56","ac":"6.72","ae":"1020","i":"12:13:33","n":"07:13:33","m":"01:51:15","k":"09:03","j":"6.64","l":"1028","S":"14:53:12","X":"09:53:12","W":"02:39:39","U":"10:51","T":"5.54","V":"1028","u":"16:32:43","z":"11:32:43","y":"01:39:31","w":"10:52","v":"5.52","x":"1016","c":"18:22:33","h":"13:22:33","g":"01:49:50","e":"10:48","d":"5.56","f":"1014","E":"19:58:01","J":"14:58:01","I":"04:09","G":"06:55","F":"8.70","H":"1012"}],"999999167888710001C6A8AF":[{"a":"2025","B":"999999167888710001C6A8AF","A":"HCH8NDMRA585ED","R":"Olsson, Andreas (SWE)","ap":"3352","C":"M21","ao":"UL90","D":"Team idiot","Y":"1066","Z":"343","aa":"1497","b":"15:40:03","an":"5.85","ar":"I mål","aq":"05:00:00","o":"05:36:07","t":"00:36:07","s":"36:07","q":"10:57","p":"5.48","r":"989","ah":"06:52:52","am":"01:52:52","al":"01:16:45","aj":"10:10","ai":"5.90","ak":"1135","K":"09:13:56","P":"04:13:56","O":"02:21:04","M":"09:44","L":"6.17","N":"1178","ab":"11:07:44","ag":"06:07:44","af":"01:53:48","ad":"10:17","ac":"5.84","ae":"1164","i":"13:17:38","n":"08:17:38","m":"02:09:54","k":"10:34","j":"5.69","l":"1161","S":"15:41:19","X":"10:41:19","W":"02:23:41","U":"09:46","T":"6.15","V":"1113","u":"17:13:03","z":"12:13:03","y":"01:31:44","w":"10:01","v":"5.99","x":"1095","c":"18:52:49","h":"13:52:49","g":"01:39:46","e":"09:49","d":"6.12","f":"1074","E":"20:40:03","J":"15:40:03","I":"05:30","G":"09:10","F":"6.55","H":"1066"}],"HCH8NDMR1CA94AF":[{"a":"2025","B":"HCH8NDMR1CA94AF","A":"HCH8NDMRA3FE0C","R":"Samuelsson, Alexander (SWE)","ap":"2395","C":"M21","ao":"UL90","D":"HÄGERSTEN","an":"6.60","ar":"Brutit","aq":"05:00:00","o":"05:38:47","t":"00:38:47","s":"38:47","q":"11:46","p":"5.11","r":"1164","ah":"06:54:40","am":"01:54:40","al":"01:15:53","aj":"10:04","ai":"5.97","ak":"1151","K":"08:51:29","P":"03:51:29","O":"01:56:49","M":"08:04","L":"7.45","N":"1101","ab":"10:27:36","ag":"05:27:36","af":"01:36:07","ad":"08:41","ac":"6.91","ae":"1063","i":"12:23:05","n":"07:23:05","m":"01:55:29","k":"09:23","j":"6.40","l":"1056"}],"99999916788859000005E2AF":[{"a":"2025","B":"99999916788859000005E2AF","A":"HCH8NDMRA408ED","R":"Stridh, Pernilla (SWE)","ap":"1174","C":"W55","ao":"UL90","D":"BROMMA","Y":"147","Z":"7","aa":"661","b":"11:45:09","an":"7.80","ar":"I mål","aq":"05:00:00","Q":"1","o":"05:33:17","t":"00:33:17","s":"33:17","q":"10:06","p":"5.95","r":"264","ah":"06:27:09","am":"01:27:09","al":"53:52","aj":"07:09","ai":"8.41","ak":"188","K":"08:11:23","P":"03:11:23","O":"01:44:14","M":"07:12","L":"8.35","N":"184","ab":"09:34:42","ag":"04:34:42","af":"01:23:19","ad":"07:32","ac":"7.97","ae":"159","i":"11:03:50","n":"06:03:50","m":"01:29:08","k":"07:15","j":"8.29","l":"143","S":"13:04:21","X":"08:04:21","W":"02:00:31","U":"08:11","T":"7.33","V":"143","u":"14:23:19","z":"09:23:19","y":"01:18:58","w":"08:38","v":"6.96","x":"150","c":"15:45:35","h":"10:45:35","g":"01:22:16","e":"08:06","d":"7.42","f":"158","E":"16:45:09","J":"11:45:09","I":"02:57","G":"04:55","F":"12.20","H":"147"}],"HCH8NDMR1CAA5AF":[{"a":"2025","B":"HCH8NDMR1CAA5AF","A":"HCH8NDMRA4939A","R":"Östensson, Elias (SWE)","ap":"2768","C":"M21","ao":"UL90","D":"Team traktor","Y":"160","Z":"44","aa":"201","b":"09:43:43","an":"9.42","ar":"I mål","aq":"05:00:00","Q":"2","o":"05:21:11","t":"00:21:11","s":"21:11","q":"06:26","p":"9.35","r":"90","ah":"06:03:57","am":"01:03:57","al":"42:46","aj":"05:40","ai":"10.59","ak":"122","K":"07:31:57","P":"02:31:57","O":"01:28:00","M":"06:05","L":"9.89","N":"173","ab":"08:38:53","ag":"03:38:53","af":"01:06:56","ad":"06:03","ac":"9.92","ae":"161","i":"10:01:07","n":"05:01:07","m":"01:22:14","k":"06:41","j":"8.98","l":"190","S":"11:29:17","X":"06:29:17","W":"01:28:10","U":"06:00","T":"10.03","V":"151","u":"12:33:14","z":"07:33:14","y":"01:03:57","w":"06:59","v":"8.59","x":"153","c":"13:42:31","h":"08:42:31","g":"01:09:17","e":"06:49","d":"8.81","f":"152","E":"14:43:43","J":"09:43:43","I":"03:11","G":"05:19","F":"11.36","H":"160"}]}