{"668981C58080D044":[{"K":"2024","aa":"668981C58080D044","Z":"EBL2024_251","ae":"Cederlöf, Jakob (UNK)","ah":"251","ab":"H","ac":"XC Sthlm Ski Club","af":"84","ag":"84","L":"03:04:41","aj":"Finished","ai":"10:00:00","G":"10:27:58","J":"00:27:59","I":"00:27:59","H":"114","a":"10:42:00","d":"00:42:01","c":"00:42:01","b":"108","e":"11:02:57","h":"01:02:58","g":"01:02:58","f":"101","i":"11:26:42","l":"01:26:43","k":"01:26:43","j":"98","m":"11:29:34","p":"01:29:34","o":"01:29:34","n":"97","q":"11:59:05","t":"01:59:06","s":"00:29:32","r":"91","u":"12:14:17","x":"02:14:18","w":"00:44:44","v":"88","y":"12:36:49","B":"02:36:50","A":"01:07:16","z":"86","C":"13:01:44","F":"03:01:45","E":"01:32:11","D":"84","V":"13:04:40","Y":"03:04:41","X":"01:35:07","W":"84","O":"1","Q":"2","S":"1","M":"4"}],"855EEEC4B4E7AE44":[{"K":"2024","aa":"855EEEC4B4E7AE44","Z":"EBL2024_6422","ae":"Neiderlöw, Joakim (UNK)","ah":"6422","ab":"H","ac":"Sya SK","af":"321","ag":"402","L":"05:58:24","aj":"Finished","ai":"10:01:51","G":"10:50:30","J":"00:48:40","I":"00:48:40","H":"288","a":"11:18:24","d":"01:16:33","c":"01:16:33","b":"304","e":"11:58:19","h":"01:56:28","g":"01:56:28","f":"320","i":"12:43:26","l":"02:41:36","k":"02:41:36","j":"327","m":"12:48:58","p":"02:47:08","o":"02:47:08","n":"325","q":"13:51:12","t":"03:49:21","s":"03:49:21","r":"329","u":"14:21:50","x":"04:19:59","w":"04:19:59","v":"325","y":"15:06:48","B":"05:04:58","A":"05:04:58","z":"322","C":"15:54:58","F":"05:53:07","E":"05:53:07","D":"321","V":"16:00:15","Y":"05:58:24","X":"05:58:24","W":"321","O":"1","Q":"16","R":"3","S":"2","T":"5","M":"27"}],"514823E52E195C44":[{"K":"2024","aa":"514823E52E195C44","Z":"EBL2024_6373","ae":"Bergroth, Magnus (UNK)","ah":"6373","ab":"H","aj":"DNF","ai":"10:01:49","G":"11:13:07","J":"01:11:19","I":"01:11:19","H":"438","a":"11:50:21","d":"01:48:33","c":"01:48:33","b":"436","e":"12:58:02","h":"02:56:14","g":"02:56:14","f":"436","i":"14:43:00","l":"04:41:12","k":"04:41:12","j":"436","m":"14:53:37","p":"04:51:49","o":"04:51:49","n":"433"},{"K":"2025","aa":"514823E52E195C44","Z":"EBL2025_6528","ae":"Bergroth, Magnus (UNK)","ah":"6528","ab":"H","aj":"DNF","ai":"10:04:19","G":"11:13:52","J":"01:09:34","I":"01:09:34","H":"526","a":"12:27:54","d":"02:23:36","c":"02:23:36","b":"528","e":"13:11:29","h":"03:07:11","g":"03:07:11","f":"527"},{"K":"2026","aa":"514823E52E195C44","Z":"EBL2026_6682","ae":"Bergroth, Magnus (UNK)","ah":"6682","ab":"H","af":"518","ag":"732","L":"07:35:20","aj":"Finished","ai":"10:02:54","G":"11:02:35","J":"00:59:41","I":"00:59:41","H":"506","a":"11:38:27","d":"01:35:33","c":"01:35:33","b":"523","e":"12:26:34","h":"02:23:41","g":"02:23:41","f":"511","i":"13:24:22","l":"03:21:28","k":"03:21:28","j":"514","m":"13:45:49","p":"03:42:56","o":"03:42:56","n":"514","q":"14:47:03","t":"04:44:10","s":"04:44:10","r":"513","u":"15:24:20","x":"05:21:26","w":"05:21:26","v":"509","y":"16:17:07","B":"06:14:14","A":"06:14:14","z":"505","C":"17:31:08","F":"07:28:15","E":"07:28:15","D":"518","V":"17:38:13","Y":"07:35:20","X":"07:35:20","W":"518","U":"1","N":"9","O":"3","P":"32","Q":"2","R":"5","S":"9","M":"61"}],"9B89F477697BE944":[{"K":"2025","aa":"9B89F477697BE944","Z":"EBL2025_36","ae":"Hermansson, John (UNK)","ah":"36","ab":"H","ad":"IFK Mora SK","ac":"IFK Mora Skidklubb","af":"9","ag":"9","L":"02:44:41","aj":"Finished","ai":"10:00:00","G":"10:20:42","J":"00:20:43","I":"00:20:43","H":"4","a":"10:38:43","d":"00:38:44","c":"00:38:44","b":"9","e":"10:49:14","h":"00:49:14","g":"00:49:14","f":"16","i":"11:14:49","l":"01:14:50","k":"00:23:09","j":"13","q":"11:44:31","t":"01:44:32","s":"00:52:51","r":"10","y":"12:10:56","B":"02:10:56","A":"00:23:52","z":"8","C":"12:31:04","F":"02:31:05","E":"00:44:00","D":"10","V":"12:44:40","Y":"02:44:41","X":"00:57:36","W":"9","O":"1","M":"1"},{"K":"2026","aa":"9B89F477697BE944","Z":"EBL2026_8","ae":"Hermansson, John (UNK)","ah":"8","ab":"H","ad":"IFK Mora SK","ac":"IFK Mora Skidklubb","af":"42","ag":"42","L":"03:00:07","aj":"Finished","ai":"10:00:00","G":"10:24:54","J":"00:24:55","I":"00:24:55","H":"15","a":"10:38:50","d":"00:38:51","c":"00:38:51","b":"16","e":"10:59:05","h":"00:59:06","g":"00:59:06","f":"17","i":"11:21:08","l":"01:21:09","k":"01:21:09","j":"18","m":"11:25:29","p":"01:25:29","o":"00:01:47","n":"16","q":"11:51:02","t":"01:51:03","s":"00:27:20","r":"18","u":"12:06:16","x":"02:06:17","w":"00:42:34","v":"27","y":"12:28:43","B":"02:28:44","A":"01:05:01","z":"28","C":"12:57:00","F":"02:57:01","E":"01:33:18","D":"42","V":"13:00:06","Y":"03:00:07","X":"00:03:06","W":"42"}],"0BACE355C007C344":[{"K":"2025","aa":"0BACE355C007C344","Z":"EBL2025_6852","ae":"Jernlöf, Mikael (UNK)","ah":"6852","ab":"H","ac":"Börje Sportklubb","af":"288","ag":"288","L":"04:10:35","aj":"Finished","ai":"10:00:00","G":"10:34:03","J":"00:34:04","I":"00:34:04","H":"378","a":"11:00:18","d":"01:00:19","c":"01:00:19","b":"364","e":"11:15:25","h":"01:15:26","g":"01:15:26","f":"363","i":"11:53:41","l":"01:53:42","k":"00:34:31","j":"337","q":"12:39:08","t":"02:39:08","s":"01:19:58","r":"314","y":"13:18:55","B":"03:18:56","A":"00:35:42","z":"291","C":"13:49:43","F":"03:49:44","E":"01:06:30","D":"289","V":"14:10:34","Y":"04:10:35","X":"01:27:20","W":"288","U":"2","N":"1","O":"26","P":"5","R":"45","T":"19","M":"98"}],"1CD015F8B5959044":[{"K":"2025","aa":"1CD015F8B5959044","Z":"EBL2025_1021","ae":"Floser, Linnea (UNK)","ah":"1021","ab":"D","ad":"XC Sthlm Ski Club","ac":"XC Sthlm Ski Club","af":"35","ag":"35","L":"04:27:07","aj":"Finished","ai":"10:00:00","G":"10:32:32","J":"00:32:33","I":"00:32:33","H":"38","a":"11:00:10","d":"01:00:11","c":"01:00:11","b":"38","e":"11:15:57","h":"01:15:58","g":"01:15:58","f":"38","i":"11:56:49","l":"01:56:50","k":"00:36:53","j":"35","q":"12:46:50","t":"02:46:51","s":"01:26:54","r":"36","y":"13:32:23","B":"03:32:24","A":"00:40:53","z":"35","C":"14:05:53","F":"04:05:54","E":"01:14:23","D":"35","V":"14:27:06","Y":"04:27:07","X":"01:35:36","W":"35","O":"3","R":"2","M":"5"},{"K":"2026","aa":"1CD015F8B5959044","Z":"EBL2026_1205","ae":"Floser, Linnea (UNK)","ah":"1205","ab":"D","ad":"XC Sthlm Ski Club","ac":"XC Sthlm Ski Club","af":"34","ag":"34","L":"04:15:03","aj":"Finished","ai":"09:45:00","G":"10:21:20","J":"00:36:21","I":"00:36:21","H":"33","a":"10:40:51","d":"00:55:51","c":"00:55:51","b":"34","e":"11:11:16","h":"01:26:17","g":"01:26:17","f":"35","i":"11:44:02","l":"01:59:03","k":"01:59:03","j":"36","m":"11:50:47","p":"02:05:48","o":"02:05:48","n":"33","q":"12:27:31","t":"02:42:32","s":"02:42:32","r":"34","u":"12:48:33","x":"03:03:34","w":"03:03:34","v":"33","y":"13:21:12","B":"03:36:13","A":"03:36:13","z":"34","C":"13:56:03","F":"04:11:04","E":"04:11:04","D":"34","V":"14:00:02","Y":"04:15:03","X":"04:15:03","W":"34","P":"2","M":"2"}],"9E6E2E3946B42C44":[{"K":"2025","aa":"9E6E2E3946B42C44","Z":"EBL2025_6163","ae":"Pettersson, Alexander (UNK)","ah":"6163","ab":"H","ac":"Ljungsbro","af":"215","ag":"255","L":"05:35:44","aj":"Finished","ai":"10:03:55","G":"10:46:24","J":"00:42:29","I":"00:42:29","H":"215","a":"11:19:10","d":"01:15:15","c":"01:15:15","b":"198","e":"11:38:36","h":"01:34:41","g":"01:34:41","f":"199","i":"12:29:22","l":"02:25:27","k":"00:46:14","j":"199","q":"13:32:17","t":"03:28:22","s":"01:49:09","r":"201","y":"14:29:03","B":"04:25:08","A":"00:51:31","z":"212","C":"15:12:30","F":"05:08:35","E":"01:34:58","D":"214","V":"15:39:39","Y":"05:35:44","X":"02:02:07","W":"215","O":"10","P":"1","R":"12","T":"1","M":"24"}],"76439D4CE9514B44":[{"K":"2025","aa":"76439D4CE9514B44","Z":"EBL2025_1351","ae":"Thimren, Berit (UNK)","ah":"1351","ab":"D","af":"123","ag":"495","L":"06:45:47","aj":"Finished","ai":"10:08:32","G":"11:01:47","J":"00:53:15","I":"00:53:15","H":"154","a":"11:43:53","d":"01:35:21","c":"01:35:21","b":"131","e":"12:08:24","h":"01:59:52","g":"01:59:52","f":"125","i":"13:10:30","l":"03:01:58","k":"00:56:01","j":"111","q":"14:23:58","t":"04:15:27","s":"02:09:29","r":"109","y":"15:32:17","B":"05:23:45","A":"00:55:35","z":"114","C":"16:23:10","F":"06:14:38","E":"01:46:28","D":"122","V":"16:54:19","Y":"06:45:47","X":"02:17:37","W":"123","O":"8","R":"7","T":"1","M":"16"}],"11572EEEA97DC744":[{"K":"2025","aa":"11572EEEA97DC744","Z":"EBL2025_1246","ae":"Maleus, Mary (UNK)","ah":"1246","ab":"D","ac":"Sundbybergs Bollklubb","aj":"DNF","ai":"10:07:03","G":"11:11:33","J":"01:04:31","I":"01:04:31","H":"254","a":"12:09:14","d":"02:02:11","c":"02:02:11","b":"255","e":"12:40:37","h":"02:33:35","g":"02:33:35","f":"248","i":"13:57:04","l":"03:50:01","k":"01:08:01","j":"232","q":"15:25:00","t":"05:17:57","s":"02:35:58","r":"234"}],"AF8FD915A28A0844":[{"K":"2026","aa":"AF8FD915A28A0844","Z":"EBL2026_6821","ae":"Bergman, Jonathan (UNK)","ah":"6821","ab":"H","ac":"Norbergs Skidklubb","af":"8","ag":"8","L":"03:39:05","aj":"Finished","ai":"10:00:28","G":"10:31:14","J":"00:30:47","I":"00:30:47","H":"3","a":"10:47:49","d":"00:47:21","c":"00:47:21","b":"3","e":"11:12:46","h":"01:12:18","g":"01:12:18","f":"5","i":"11:41:08","l":"01:40:41","k":"01:40:41","j":"5","m":"11:47:12","p":"01:46:44","o":"01:46:44","n":"5","q":"12:18:17","t":"02:17:50","s":"02:17:50","r":"4","u":"12:37:09","x":"02:36:41","w":"02:36:41","v":"6","y":"13:06:20","B":"03:05:52","A":"03:05:52","z":"7","C":"13:35:51","F":"03:35:24","E":"03:35:24","D":"8","V":"13:39:32","Y":"03:39:05","X":"03:39:05","W":"8"}],"9E3D538A4333E144":[{"K":"2026","aa":"9E3D538A4333E144","Z":"EBL2026_1351","ae":"Alarcon, Aura (UNK)","ah":"1351","ab":"D","af":"48","ag":"292","L":"05:32:25","aj":"Finished","ai":"10:02:25","G":"10:51:15","J":"00:48:51","I":"00:48:51","H":"58","a":"11:14:51","d":"01:12:27","c":"01:12:27","b":"43","e":"11:52:28","h":"01:50:03","g":"01:50:03","f":"42","i":"12:31:57","l":"02:29:33","k":"02:29:33","j":"40","m":"12:42:05","p":"02:39:41","o":"02:39:41","n":"37","q":"13:29:05","t":"03:26:41","s":"03:26:41","r":"39","u":"13:59:58","x":"03:57:34","w":"03:57:34","v":"43","y":"14:43:48","B":"04:41:24","A":"04:41:24","z":"46","C":"15:29:12","F":"05:26:48","E":"05:26:48","D":"47","V":"15:34:50","Y":"05:32:25","X":"05:32:25","W":"48","N":"1","P":"2","M":"3"}],"E14ED59DAFD44944":[{"K":"2026","aa":"E14ED59DAFD44944","Z":"EBL2026_6904","ae":"Holmén, Fredrik (UNK)","ah":"6904","ab":"H","ac":"AXA Sports Club","af":"455","ag":"598","L":"06:53:48","aj":"Finished","ai":"10:10:45","G":"11:11:21","J":"01:00:36","I":"01:00:36","H":"514","a":"11:44:18","d":"01:33:34","c":"01:33:34","b":"508","e":"12:31:02","h":"02:20:18","g":"02:20:18","f":"498","i":"13:23:52","l":"03:13:08","k":"03:13:08","j":"490","m":"13:37:04","p":"03:26:20","o":"03:26:20","n":"474","q":"14:36:35","t":"04:25:51","s":"04:25:51","r":"471","u":"15:13:10","x":"05:02:26","w":"05:02:26","v":"467","y":"16:03:24","B":"05:52:40","A":"05:52:40","z":"459","C":"16:58:05","F":"06:47:21","E":"06:47:21","D":"455","V":"17:04:32","Y":"06:53:48","X":"06:53:48","W":"455","U":"1","N":"9","O":"3","P":"31","Q":"2","R":"4","S":"9","M":"59"}],"657A8ADA7F6FB944":[{"K":"2026","aa":"657A8ADA7F6FB944","Z":"EBL2026_6301","ae":"Johnson, Kenneth (UNK)","ah":"6301","ab":"H","af":"475","ag":"642","L":"07:05:49","aj":"Finished","ai":"10:03:58","G":"11:04:41","J":"01:00:44","I":"01:00:44","H":"517","a":"11:36:23","d":"01:32:25","c":"01:32:25","b":"504","e":"12:25:24","h":"02:21:26","g":"02:21:26","f":"501","i":"13:20:34","l":"03:16:36","k":"03:16:36","j":"502","m":"13:33:31","p":"03:29:33","o":"03:29:33","n":"492","q":"14:34:14","t":"04:30:16","s":"04:30:16","r":"488","u":"15:10:57","x":"05:06:59","w":"05:06:59","v":"479","y":"16:03:46","B":"05:59:48","A":"05:59:48","z":"473","C":"17:03:02","F":"06:59:04","E":"06:59:04","D":"475","V":"17:09:47","Y":"07:05:49","X":"07:05:49","W":"475","U":"1","N":"9","O":"3","P":"32","Q":"2","R":"4","S":"9","M":"60"}],"2D710F32ED67DB44":[{"K":"2026","aa":"2D710F32ED67DB44","Z":"EBL2026_9210","ae":"Alfonsi, Caroline (UNK)","ah":"9210","ab":"D","ac":"AXA Sports Club","aj":"Did not start","ai":"10:00:00"}]}